[{"timestamp":1702555200000,"ticks":[{"pool":{"_bn":"e4970eb646bcfb392ded0a23e207a34043c90212678fded18b70ae3efe7a2610"},"index":27725,"sign":true,"liquidityChange":{"v":"922a6692a3a8b3"},"liquidityGross":{"v":"922a6692a3a8b3"},"sqrtPrice":{"v":"034eefc9ab33e0e017b000"},"feeGrowthOutsideX":{"v":"00"},"feeGrowthOutsideY":{"v":"00"},"secondsPerLiquidityOutside":{"v":"00"},"secondsOutside":"00","bump":255},{"pool":{"_bn":"e4970eb646bcfb392ded0a23e207a34043c90212678fded18b70ae3efe7a2610"},"index":28465,"sign":true,"liquidityChange":{"v":"0603695f215e366f"},"liquidityGross":{"v":"0603695f215e366f"},"sqrtPrice":{"v":"036edbd04644aae973e000"},"feeGrowthOutsideX":{"v":"00"},"feeGrowthOutsideY":{"v":"00"},"secondsPerLiquidityOutside":{"v":"00"},"secondsOutside":"34","bump":253},{"pool":{"_bn":"e4970eb646bcfb392ded0a23e207a34043c90212678fded18b70ae3efe7a2610"},"index":29345,"sign":false,"liquidityChange":{"v":"0603695f215e366f"},"liquidityGross":{"v":"0603695f215e366f"},"sqrtPrice":{"v":"039663c72dbecb6eebb000"},"feeGrowthOutsideX":{"v":"1be2130ac9318c30"},"feeGrowthOutsideY":{"v":"0216207f6519e7e560"},"secondsPerLiquidityOutside":{"v":"1dc071"},"secondsOutside":"01395b","bump":255},{"pool":{"_bn":"e4970eb646bcfb392ded0a23e207a34043c90212678fded18b70ae3efe7a2610"},"index":29960,"sign":false,"liquidityChange":{"v":"922a6692a3a8b3"},"liquidityGross":{"v":"922a6692a3a8b3"},"sqrtPrice":{"v":"03b31145ace032b0311000"},"feeGrowthOutsideX":{"v":"00"},"feeGrowthOutsideY":{"v":"00"},"secondsPerLiquidityOutside":{"v":"00"},"secondsOutside":"00","bump":252}],"volumeX":"539000000","volumeY":"49985600000"},{"timestamp":1702641600000,"ticks":[{"pool":{"_bn":"e4970eb646bcfb392ded0a23e207a34043c90212678fded18b70ae3efe7a2610"},"index":27725,"sign":true,"liquidityChange":{"v":"922a6692a3a8b3"},"liquidityGross":{"v":"922a6692a3a8b3"},"sqrtPrice":{"v":"034eefc9ab33e0e017b000"},"feeGrowthOutsideX":{"v":"00"},"feeGrowthOutsideY":{"v":"00"},"secondsPerLiquidityOutside":{"v":"00"},"secondsOutside":"00","bump":255},{"pool":{"_bn":"e4970eb646bcfb392ded0a23e207a34043c90212678fded18b70ae3efe7a2610"},"index":28465,"sign":true,"liquidityChange":{"v":"0603695f215e366f"},"liquidityGross":{"v":"0603695f215e366f"},"sqrtPrice":{"v":"036edbd04644aae973e000"},"feeGrowthOutsideX":{"v":"00"},"feeGrowthOutsideY":{"v":"00"},"secondsPerLiquidityOutside":{"v":"00"},"secondsOutside":"34","bump":253},{"pool":{"_bn":"e4970eb646bcfb392ded0a23e207a34043c90212678fded18b70ae3efe7a2610"},"index":29345,"sign":false,"liquidityChange":{"v":"0603695f215e366f"},"liquidityGross":{"v":"0603695f215e366f"},"sqrtPrice":{"v":"039663c72dbecb6eebb000"},"feeGrowthOutsideX":{"v":"1be2130ac9318c30"},"feeGrowthOutsideY":{"v":"0216207f6519e7e560"},"secondsPerLiquidityOutside":{"v":"1dc071"},"secondsOutside":"01395b","bump":255},{"pool":{"_bn":"e4970eb646bcfb392ded0a23e207a34043c90212678fded18b70ae3efe7a2610"},"index":29960,"sign":false,"liquidityChange":{"v":"922a6692a3a8b3"},"liquidityGross":{"v":"922a6692a3a8b3"},"sqrtPrice":{"v":"03b31145ace032b0311000"},"feeGrowthOutsideX":{"v":"00"},"feeGrowthOutsideY":{"v":"00"},"secondsPerLiquidityOutside":{"v":"00"},"secondsOutside":"00","bump":252}],"volumeX":"539000000","volumeY":"49985600000"},{"timestamp":1702728000000,"ticks":[{"pool":{"_bn":"e4970eb646bcfb392ded0a23e207a34043c90212678fded18b70ae3efe7a2610"},"index":27725,"sign":true,"liquidityChange":{"v":"922a6692a3a8b3"},"liquidityGross":{"v":"922a6692a3a8b3"},"sqrtPrice":{"v":"034eefc9ab33e0e017b000"},"feeGrowthOutsideX":{"v":"00"},"feeGrowthOutsideY":{"v":"00"},"secondsPerLiquidityOutside":{"v":"00"},"secondsOutside":"00","bump":255},{"pool":{"_bn":"e4970eb646bcfb392ded0a23e207a34043c90212678fded18b70ae3efe7a2610"},"index":28465,"sign":true,"liquidityChange":{"v":"0603695f215e366f"},"liquidityGross":{"v":"0603695f215e366f"},"sqrtPrice":{"v":"036edbd04644aae973e000"},"feeGrowthOutsideX":{"v":"00"},"feeGrowthOutsideY":{"v":"00"},"secondsPerLiquidityOutside":{"v":"00"},"secondsOutside":"34","bump":253},{"pool":{"_bn":"e4970eb646bcfb392ded0a23e207a34043c90212678fded18b70ae3efe7a2610"},"index":29345,"sign":false,"liquidityChange":{"v":"0603695f215e366f"},"liquidityGross":{"v":"0603695f215e366f"},"sqrtPrice":{"v":"039663c72dbecb6eebb000"},"feeGrowthOutsideX":{"v":"1be2130ac9318c30"},"feeGrowthOutsideY":{"v":"0216207f6519e7e560"},"secondsPerLiquidityOutside":{"v":"1dc071"},"secondsOutside":"01395b","bump":255},{"pool":{"_bn":"e4970eb646bcfb392ded0a23e207a34043c90212678fded18b70ae3efe7a2610"},"index":29960,"sign":false,"liquidityChange":{"v":"922a6692a3a8b3"},"liquidityGross":{"v":"922a6692a3a8b3"},"sqrtPrice":{"v":"03b31145ace032b0311000"},"feeGrowthOutsideX":{"v":"00"},"feeGrowthOutsideY":{"v":"00"},"secondsPerLiquidityOutside":{"v":"00"},"secondsOutside":"00","bump":252}],"volumeX":"539000000","volumeY":"49985600000"},{"timestamp":1702814400000,"ticks":[{"pool":{"_bn":"e4970eb646bcfb392ded0a23e207a34043c90212678fded18b70ae3efe7a2610"},"index":27725,"sign":true,"liquidityChange":{"v":"922a6692a3a8b3"},"liquidityGross":{"v":"922a6692a3a8b3"},"sqrtPrice":{"v":"034eefc9ab33e0e017b000"},"feeGrowthOutsideX":{"v":"00"},"feeGrowthOutsideY":{"v":"00"},"secondsPerLiquidityOutside":{"v":"00"},"secondsOutside":"00","bump":255},{"pool":{"_bn":"e4970eb646bcfb392ded0a23e207a34043c90212678fded18b70ae3efe7a2610"},"index":28465,"sign":true,"liquidityChange":{"v":"0603695f215e366f"},"liquidityGross":{"v":"0603695f215e366f"},"sqrtPrice":{"v":"036edbd04644aae973e000"},"feeGrowthOutsideX":{"v":"00"},"feeGrowthOutsideY":{"v":"00"},"secondsPerLiquidityOutside":{"v":"00"},"secondsOutside":"34","bump":253},{"pool":{"_bn":"e4970eb646bcfb392ded0a23e207a34043c90212678fded18b70ae3efe7a2610"},"index":29345,"sign":false,"liquidityChange":{"v":"0603695f215e366f"},"liquidityGross":{"v":"0603695f215e366f"},"sqrtPrice":{"v":"039663c72dbecb6eebb000"},"feeGrowthOutsideX":{"v":"1be2130ac9318c30"},"feeGrowthOutsideY":{"v":"0216207f6519e7e560"},"secondsPerLiquidityOutside":{"v":"1dc071"},"secondsOutside":"01395b","bump":255},{"pool":{"_bn":"e4970eb646bcfb392ded0a23e207a34043c90212678fded18b70ae3efe7a2610"},"index":29960,"sign":false,"liquidityChange":{"v":"922a6692a3a8b3"},"liquidityGross":{"v":"922a6692a3a8b3"},"sqrtPrice":{"v":"03b31145ace032b0311000"},"feeGrowthOutsideX":{"v":"00"},"feeGrowthOutsideY":{"v":"00"},"secondsPerLiquidityOutside":{"v":"00"},"secondsOutside":"00","bump":252}],"volumeX":"539000000","volumeY":"49985600000"},{"timestamp":1702900800000,"ticks":[{"pool":{"_bn":"e4970eb646bcfb392ded0a23e207a34043c90212678fded18b70ae3efe7a2610"},"index":27725,"sign":true,"liquidityChange":{"v":"922a6692a3a8b3"},"liquidityGross":{"v":"922a6692a3a8b3"},"sqrtPrice":{"v":"034eefc9ab33e0e017b000"},"feeGrowthOutsideX":{"v":"00"},"feeGrowthOutsideY":{"v":"00"},"secondsPerLiquidityOutside":{"v":"00"},"secondsOutside":"00","bump":255},{"pool":{"_bn":"e4970eb646bcfb392ded0a23e207a34043c90212678fded18b70ae3efe7a2610"},"index":28465,"sign":true,"liquidityChange":{"v":"0603695f215e366f"},"liquidityGross":{"v":"0603695f215e366f"},"sqrtPrice":{"v":"036edbd04644aae973e000"},"feeGrowthOutsideX":{"v":"00"},"feeGrowthOutsideY":{"v":"00"},"secondsPerLiquidityOutside":{"v":"00"},"secondsOutside":"34","bump":253},{"pool":{"_bn":"e4970eb646bcfb392ded0a23e207a34043c90212678fded18b70ae3efe7a2610"},"index":29345,"sign":false,"liquidityChange":{"v":"0603695f215e366f"},"liquidityGross":{"v":"0603695f215e366f"},"sqrtPrice":{"v":"039663c72dbecb6eebb000"},"feeGrowthOutsideX":{"v":"1be2130ac9318c30"},"feeGrowthOutsideY":{"v":"0216207f6519e7e560"},"secondsPerLiquidityOutside":{"v":"1dc071"},"secondsOutside":"01395b","bump":255},{"pool":{"_bn":"e4970eb646bcfb392ded0a23e207a34043c90212678fded18b70ae3efe7a2610"},"index":29960,"sign":false,"liquidityChange":{"v":"922a6692a3a8b3"},"liquidityGross":{"v":"922a6692a3a8b3"},"sqrtPrice":{"v":"03b31145ace032b0311000"},"feeGrowthOutsideX":{"v":"00"},"feeGrowthOutsideY":{"v":"00"},"secondsPerLiquidityOutside":{"v":"00"},"secondsOutside":"00","bump":252}],"volumeX":"539000000","volumeY":"49985600000"},{"timestamp":1702987200000,"ticks":[{"pool":{"_bn":"e4970eb646bcfb392ded0a23e207a34043c90212678fded18b70ae3efe7a2610"},"index":27725,"sign":true,"liquidityChange":{"v":"922a6692a3a8b3"},"liquidityGross":{"v":"922a6692a3a8b3"},"sqrtPrice":{"v":"034eefc9ab33e0e017b000"},"feeGrowthOutsideX":{"v":"00"},"feeGrowthOutsideY":{"v":"00"},"secondsPerLiquidityOutside":{"v":"00"},"secondsOutside":"00","bump":255},{"pool":{"_bn":"e4970eb646bcfb392ded0a23e207a34043c90212678fded18b70ae3efe7a2610"},"index":28465,"sign":true,"liquidityChange":{"v":"0603695f215e366f"},"liquidityGross":{"v":"0603695f215e366f"},"sqrtPrice":{"v":"036edbd04644aae973e000"},"feeGrowthOutsideX":{"v":"00"},"feeGrowthOutsideY":{"v":"00"},"secondsPerLiquidityOutside":{"v":"00"},"secondsOutside":"34","bump":253},{"pool":{"_bn":"e4970eb646bcfb392ded0a23e207a34043c90212678fded18b70ae3efe7a2610"},"index":29345,"sign":false,"liquidityChange":{"v":"0603695f215e366f"},"liquidityGross":{"v":"0603695f215e366f"},"sqrtPrice":{"v":"039663c72dbecb6eebb000"},"feeGrowthOutsideX":{"v":"1be2130ac9318c30"},"feeGrowthOutsideY":{"v":"0216207f6519e7e560"},"secondsPerLiquidityOutside":{"v":"1dc071"},"secondsOutside":"01395b","bump":255},{"pool":{"_bn":"e4970eb646bcfb392ded0a23e207a34043c90212678fded18b70ae3efe7a2610"},"index":29960,"sign":false,"liquidityChange":{"v":"922a6692a3a8b3"},"liquidityGross":{"v":"922a6692a3a8b3"},"sqrtPrice":{"v":"03b31145ace032b0311000"},"feeGrowthOutsideX":{"v":"00"},"feeGrowthOutsideY":{"v":"00"},"secondsPerLiquidityOutside":{"v":"00"},"secondsOutside":"00","bump":252}],"volumeX":"539000000","volumeY":"49985600000"},{"timestamp":1703073600000,"ticks":[{"pool":{"_bn":"e4970eb646bcfb392ded0a23e207a34043c90212678fded18b70ae3efe7a2610"},"index":27725,"sign":true,"liquidityChange":{"v":"922a6692a3a8b3"},"liquidityGross":{"v":"922a6692a3a8b3"},"sqrtPrice":{"v":"034eefc9ab33e0e017b000"},"feeGrowthOutsideX":{"v":"00"},"feeGrowthOutsideY":{"v":"00"},"secondsPerLiquidityOutside":{"v":"00"},"secondsOutside":"00","bump":255},{"pool":{"_bn":"e4970eb646bcfb392ded0a23e207a34043c90212678fded18b70ae3efe7a2610"},"index":28465,"sign":true,"liquidityChange":{"v":"0603695f215e366f"},"liquidityGross":{"v":"0603695f215e366f"},"sqrtPrice":{"v":"036edbd04644aae973e000"},"feeGrowthOutsideX":{"v":"00"},"feeGrowthOutsideY":{"v":"00"},"secondsPerLiquidityOutside":{"v":"00"},"secondsOutside":"34","bump":253},{"pool":{"_bn":"e4970eb646bcfb392ded0a23e207a34043c90212678fded18b70ae3efe7a2610"},"index":29345,"sign":false,"liquidityChange":{"v":"0603695f215e366f"},"liquidityGross":{"v":"0603695f215e366f"},"sqrtPrice":{"v":"039663c72dbecb6eebb000"},"feeGrowthOutsideX":{"v":"1be2130ac9318c30"},"feeGrowthOutsideY":{"v":"0216207f6519e7e560"},"secondsPerLiquidityOutside":{"v":"1dc071"},"secondsOutside":"01395b","bump":255},{"pool":{"_bn":"e4970eb646bcfb392ded0a23e207a34043c90212678fded18b70ae3efe7a2610"},"index":29960,"sign":false,"liquidityChange":{"v":"922a6692a3a8b3"},"liquidityGross":{"v":"922a6692a3a8b3"},"sqrtPrice":{"v":"03b31145ace032b0311000"},"feeGrowthOutsideX":{"v":"00"},"feeGrowthOutsideY":{"v":"00"},"secondsPerLiquidityOutside":{"v":"00"},"secondsOutside":"00","bump":252}],"volumeX":"539000000","volumeY":"49985600000"},{"timestamp":1703160000000,"ticks":[{"pool":{"_bn":"e4970eb646bcfb392ded0a23e207a34043c90212678fded18b70ae3efe7a2610"},"index":27725,"sign":true,"liquidityChange":{"v":"922a6692a3a8b3"},"liquidityGross":{"v":"922a6692a3a8b3"},"sqrtPrice":{"v":"034eefc9ab33e0e017b000"},"feeGrowthOutsideX":{"v":"00"},"feeGrowthOutsideY":{"v":"00"},"secondsPerLiquidityOutside":{"v":"00"},"secondsOutside":"00","bump":255},{"pool":{"_bn":"e4970eb646bcfb392ded0a23e207a34043c90212678fded18b70ae3efe7a2610"},"index":28465,"sign":true,"liquidityChange":{"v":"0603695f215e366f"},"liquidityGross":{"v":"0603695f215e366f"},"sqrtPrice":{"v":"036edbd04644aae973e000"},"feeGrowthOutsideX":{"v":"00"},"feeGrowthOutsideY":{"v":"00"},"secondsPerLiquidityOutside":{"v":"00"},"secondsOutside":"34","bump":253},{"pool":{"_bn":"e4970eb646bcfb392ded0a23e207a34043c90212678fded18b70ae3efe7a2610"},"index":29345,"sign":false,"liquidityChange":{"v":"0603695f215e366f"},"liquidityGross":{"v":"0603695f215e366f"},"sqrtPrice":{"v":"039663c72dbecb6eebb000"},"feeGrowthOutsideX":{"v":"1be2130ac9318c30"},"feeGrowthOutsideY":{"v":"0216207f6519e7e560"},"secondsPerLiquidityOutside":{"v":"1dc071"},"secondsOutside":"01395b","bump":255},{"pool":{"_bn":"e4970eb646bcfb392ded0a23e207a34043c90212678fded18b70ae3efe7a2610"},"index":29960,"sign":false,"liquidityChange":{"v":"922a6692a3a8b3"},"liquidityGross":{"v":"922a6692a3a8b3"},"sqrtPrice":{"v":"03b31145ace032b0311000"},"feeGrowthOutsideX":{"v":"00"},"feeGrowthOutsideY":{"v":"00"},"secondsPerLiquidityOutside":{"v":"00"},"secondsOutside":"00","bump":252}],"volumeX":"539000000","volumeY":"49985600000"}]