[{"timestamp":1713873600000,"ticks":[],"volumeX":"856109000000","volumeY":"1290637000000"},{"timestamp":1714046400000,"ticks":[],"volumeX":"856109000000","volumeY":"1290637000000"},{"timestamp":1714132800000,"ticks":[],"volumeX":"856109000000","volumeY":"1290637000000"},{"timestamp":1714219200000,"ticks":[],"volumeX":"856109000000","volumeY":"1290637000000"},{"timestamp":1714305600000,"ticks":[],"volumeX":"856109000000","volumeY":"1290637000000"},{"timestamp":1714392000000,"ticks":[],"volumeX":"856109000000","volumeY":"1290637000000"},{"timestamp":1714478400000,"ticks":[],"volumeX":"856109000000","volumeY":"1290637000000"},{"timestamp":1714564800000,"ticks":[{"pool":{"_bn":"396c5afe5531d1ef1262540002bcd24393ef322cd9ce7dc7363deaa3d81ffe83"},"index":994,"sign":true,"liquidityChange":{"v":"05d784aa3eaa6c7600"},"liquidityGross":{"v":"05d784aa3eaa6c7600"},"sqrtPrice":{"v":"de8c48d2ed78ea735000"},"feeGrowthOutsideX":{"v":"081962ad9da1d49f"},"feeGrowthOutsideY":{"v":"0adee635faedccc7"},"secondsPerLiquidityOutside":{"v":"0e50"},"secondsOutside":"5fe870","bump":255},{"pool":{"_bn":"396c5afe5531d1ef1262540002bcd24393ef322cd9ce7dc7363deaa3d81ffe83"},"index":1001,"sign":false,"liquidityChange":{"v":"05d784aa3eaa6c7600"},"liquidityGross":{"v":"05d784aa3eaa6c7600"},"sqrtPrice":{"v":"dea03a2dc2eb95926000"},"feeGrowthOutsideX":{"v":"00"},"feeGrowthOutsideY":{"v":"00"},"secondsPerLiquidityOutside":{"v":"00"},"secondsOutside":"00","bump":255}],"volumeX":"992107000000","volumeY":"1444293000000"}]