[{"timestamp":1659787200000,"ticks":[{"pool":{"_bn":"1570e38b95fe5780c18b5e5677a7bc7091fe4b9b678d511032b7f7ac2a7bd5c3"},"index":-42800,"sign":false,"liquidityChange":{"v":"03111bd4fcff75"},"liquidityGross":{"v":"03111bd4fcff75"},"sqrtPrice":{"v":"18eac3a7390b98ee2000"},"feeGrowthOutsideX":{"v":"00"},"feeGrowthOutsideY":{"v":"00"},"secondsPerLiquidityOutside":{"v":"00"},"secondsOutside":"00","bump":251},{"pool":{"_bn":"1570e38b95fe5780c18b5e5677a7bc7091fe4b9b678d511032b7f7ac2a7bd5c3"},"index":-44800,"sign":true,"liquidityChange":{"v":"03111bd4fcff75"},"liquidityGross":{"v":"03111bd4fcff75"},"sqrtPrice":{"v":"168bc600cd8c58bcf000"},"feeGrowthOutsideX":{"v":"01e9f23258234723e0fe"},"feeGrowthOutsideY":{"v":"04f68728c83334dcfd"},"secondsPerLiquidityOutside":{"v":"28174a41"},"secondsOutside":"44d43c","bump":255},{"pool":{"_bn":"1570e38b95fe5780c18b5e5677a7bc7091fe4b9b678d511032b7f7ac2a7bd5c3"},"index":-43900,"sign":true,"liquidityChange":{"v":"1896c681e572aecb"},"liquidityGross":{"v":"1896c681e572aecb"},"sqrtPrice":{"v":"17956c185245d62ef000"},"feeGrowthOutsideX":{"v":"029efb1aa549741d5191"},"feeGrowthOutsideY":{"v":"071c124329f1314620"},"secondsPerLiquidityOutside":{"v":"2818f2f7"},"secondsOutside":"44d724","bump":255},{"pool":{"_bn":"1570e38b95fe5780c18b5e5677a7bc7091fe4b9b678d511032b7f7ac2a7bd5c3"},"index":-40200,"sign":false,"liquidityChange":{"v":"17d344798f0cc0"},"liquidityGross":{"v":"17d344798f0cc0"},"sqrtPrice":{"v":"1c60454529aa647b9000"},"feeGrowthOutsideX":{"v":"00"},"feeGrowthOutsideY":{"v":"00"},"secondsPerLiquidityOutside":{"v":"00"},"secondsOutside":"00","bump":254},{"pool":{"_bn":"1570e38b95fe5780c18b5e5677a7bc7091fe4b9b678d511032b7f7ac2a7bd5c3"},"index":-47600,"sign":true,"liquidityChange":{"v":"17d344798f0cc0"},"liquidityGross":{"v":"17d344798f0cc0"},"sqrtPrice":{"v":"1399c61e8b740225b000"},"feeGrowthOutsideX":{"v":"2d24a4f3781bd3dfad"},"feeGrowthOutsideY":{"v":"751df97e2f614a30"},"secondsPerLiquidityOutside":{"v":"2c"},"secondsOutside":"14080d","bump":254},{"pool":{"_bn":"1570e38b95fe5780c18b5e5677a7bc7091fe4b9b678d511032b7f7ac2a7bd5c3"},"index":-43700,"sign":false,"liquidityChange":{"v":"1896c681e572aecb"},"liquidityGross":{"v":"1896c681e572aecb"},"sqrtPrice":{"v":"17d218a716af0f63f000"},"feeGrowthOutsideX":{"v":"00"},"feeGrowthOutsideY":{"v":"00"},"secondsPerLiquidityOutside":{"v":"00"},"secondsOutside":"00","bump":251}],"volumeX":"316524086500","volumeY":"3360875000"},{"timestamp":1659873600000,"ticks":[{"pool":{"_bn":"1570e38b95fe5780c18b5e5677a7bc7091fe4b9b678d511032b7f7ac2a7bd5c3"},"index":-42800,"sign":false,"liquidityChange":{"v":"03111bd4fcff75"},"liquidityGross":{"v":"03111bd4fcff75"},"sqrtPrice":{"v":"18eac3a7390b98ee2000"},"feeGrowthOutsideX":{"v":"00"},"feeGrowthOutsideY":{"v":"00"},"secondsPerLiquidityOutside":{"v":"00"},"secondsOutside":"00","bump":251},{"pool":{"_bn":"1570e38b95fe5780c18b5e5677a7bc7091fe4b9b678d511032b7f7ac2a7bd5c3"},"index":-44800,"sign":true,"liquidityChange":{"v":"03111bd4fcff75"},"liquidityGross":{"v":"03111bd4fcff75"},"sqrtPrice":{"v":"168bc600cd8c58bcf000"},"feeGrowthOutsideX":{"v":"01e9f23258234723e0fe"},"feeGrowthOutsideY":{"v":"04f68728c83334dcfd"},"secondsPerLiquidityOutside":{"v":"28174a41"},"secondsOutside":"44d43c","bump":255},{"pool":{"_bn":"1570e38b95fe5780c18b5e5677a7bc7091fe4b9b678d511032b7f7ac2a7bd5c3"},"index":-43900,"sign":true,"liquidityChange":{"v":"1896c681e572aecb"},"liquidityGross":{"v":"1896c681e572aecb"},"sqrtPrice":{"v":"17956c185245d62ef000"},"feeGrowthOutsideX":{"v":"029efb1aa549741d5191"},"feeGrowthOutsideY":{"v":"071c124329f1314620"},"secondsPerLiquidityOutside":{"v":"2818f2f7"},"secondsOutside":"44d724","bump":255},{"pool":{"_bn":"1570e38b95fe5780c18b5e5677a7bc7091fe4b9b678d511032b7f7ac2a7bd5c3"},"index":-40200,"sign":false,"liquidityChange":{"v":"17d344798f0cc0"},"liquidityGross":{"v":"17d344798f0cc0"},"sqrtPrice":{"v":"1c60454529aa647b9000"},"feeGrowthOutsideX":{"v":"00"},"feeGrowthOutsideY":{"v":"00"},"secondsPerLiquidityOutside":{"v":"00"},"secondsOutside":"00","bump":254},{"pool":{"_bn":"1570e38b95fe5780c18b5e5677a7bc7091fe4b9b678d511032b7f7ac2a7bd5c3"},"index":-47600,"sign":true,"liquidityChange":{"v":"17d344798f0cc0"},"liquidityGross":{"v":"17d344798f0cc0"},"sqrtPrice":{"v":"1399c61e8b740225b000"},"feeGrowthOutsideX":{"v":"2d24a4f3781bd3dfad"},"feeGrowthOutsideY":{"v":"751df97e2f614a30"},"secondsPerLiquidityOutside":{"v":"2c"},"secondsOutside":"14080d","bump":254},{"pool":{"_bn":"1570e38b95fe5780c18b5e5677a7bc7091fe4b9b678d511032b7f7ac2a7bd5c3"},"index":-43700,"sign":false,"liquidityChange":{"v":"1896c681e572aecb"},"liquidityGross":{"v":"1896c681e572aecb"},"sqrtPrice":{"v":"17d218a716af0f63f000"},"feeGrowthOutsideX":{"v":"00"},"feeGrowthOutsideY":{"v":"00"},"secondsPerLiquidityOutside":{"v":"00"},"secondsOutside":"00","bump":251}],"volumeX":"316524086500","volumeY":"3360875000"},{"timestamp":1659960000000,"ticks":[{"pool":{"_bn":"1570e38b95fe5780c18b5e5677a7bc7091fe4b9b678d511032b7f7ac2a7bd5c3"},"index":-43900,"sign":true,"liquidityChange":{"v":"1896c681e572aecb"},"liquidityGross":{"v":"1896c681e572aecb"},"sqrtPrice":{"v":"17956c185245d62ef000"},"feeGrowthOutsideX":{"v":"029efb1aa549741d5191"},"feeGrowthOutsideY":{"v":"071c124329f1314620"},"secondsPerLiquidityOutside":{"v":"2818f2f7"},"secondsOutside":"44d724","bump":255},{"pool":{"_bn":"1570e38b95fe5780c18b5e5677a7bc7091fe4b9b678d511032b7f7ac2a7bd5c3"},"index":-47600,"sign":true,"liquidityChange":{"v":"17d344798f0cc0"},"liquidityGross":{"v":"17d344798f0cc0"},"sqrtPrice":{"v":"1399c61e8b740225b000"},"feeGrowthOutsideX":{"v":"2d24a4f3781bd3dfad"},"feeGrowthOutsideY":{"v":"751df97e2f614a30"},"secondsPerLiquidityOutside":{"v":"2c"},"secondsOutside":"14080d","bump":254},{"pool":{"_bn":"1570e38b95fe5780c18b5e5677a7bc7091fe4b9b678d511032b7f7ac2a7bd5c3"},"index":-44800,"sign":true,"liquidityChange":{"v":"03111bd4fcff75"},"liquidityGross":{"v":"03111bd4fcff75"},"sqrtPrice":{"v":"168bc600cd8c58bcf000"},"feeGrowthOutsideX":{"v":"01e9f23258234723e0fe"},"feeGrowthOutsideY":{"v":"04f68728c83334dcfd"},"secondsPerLiquidityOutside":{"v":"28174a41"},"secondsOutside":"44d43c","bump":255},{"pool":{"_bn":"1570e38b95fe5780c18b5e5677a7bc7091fe4b9b678d511032b7f7ac2a7bd5c3"},"index":-40200,"sign":false,"liquidityChange":{"v":"17d344798f0cc0"},"liquidityGross":{"v":"17d344798f0cc0"},"sqrtPrice":{"v":"1c60454529aa647b9000"},"feeGrowthOutsideX":{"v":"00"},"feeGrowthOutsideY":{"v":"00"},"secondsPerLiquidityOutside":{"v":"00"},"secondsOutside":"00","bump":254},{"pool":{"_bn":"1570e38b95fe5780c18b5e5677a7bc7091fe4b9b678d511032b7f7ac2a7bd5c3"},"index":-43700,"sign":false,"liquidityChange":{"v":"1896c681e572aecb"},"liquidityGross":{"v":"1896c681e572aecb"},"sqrtPrice":{"v":"17d218a716af0f63f000"},"feeGrowthOutsideX":{"v":"00"},"feeGrowthOutsideY":{"v":"00"},"secondsPerLiquidityOutside":{"v":"00"},"secondsOutside":"00","bump":251},{"pool":{"_bn":"1570e38b95fe5780c18b5e5677a7bc7091fe4b9b678d511032b7f7ac2a7bd5c3"},"index":-42800,"sign":false,"liquidityChange":{"v":"03111bd4fcff75"},"liquidityGross":{"v":"03111bd4fcff75"},"sqrtPrice":{"v":"18eac3a7390b98ee2000"},"feeGrowthOutsideX":{"v":"00"},"feeGrowthOutsideY":{"v":"00"},"secondsPerLiquidityOutside":{"v":"00"},"secondsOutside":"00","bump":251}],"volumeX":"316524086500","volumeY":"3360875000"},{"timestamp":1660046400000,"ticks":[{"pool":{"_bn":"1570e38b95fe5780c18b5e5677a7bc7091fe4b9b678d511032b7f7ac2a7bd5c3"},"index":-42800,"sign":false,"liquidityChange":{"v":"03111bd4fcff75"},"liquidityGross":{"v":"03111bd4fcff75"},"sqrtPrice":{"v":"18eac3a7390b98ee2000"},"feeGrowthOutsideX":{"v":"00"},"feeGrowthOutsideY":{"v":"00"},"secondsPerLiquidityOutside":{"v":"00"},"secondsOutside":"00","bump":251},{"pool":{"_bn":"1570e38b95fe5780c18b5e5677a7bc7091fe4b9b678d511032b7f7ac2a7bd5c3"},"index":-44800,"sign":true,"liquidityChange":{"v":"03111bd4fcff75"},"liquidityGross":{"v":"03111bd4fcff75"},"sqrtPrice":{"v":"168bc600cd8c58bcf000"},"feeGrowthOutsideX":{"v":"01e9f23258234723e0fe"},"feeGrowthOutsideY":{"v":"04f68728c83334dcfd"},"secondsPerLiquidityOutside":{"v":"28174a41"},"secondsOutside":"44d43c","bump":255},{"pool":{"_bn":"1570e38b95fe5780c18b5e5677a7bc7091fe4b9b678d511032b7f7ac2a7bd5c3"},"index":-43900,"sign":true,"liquidityChange":{"v":"1896c681e572aecb"},"liquidityGross":{"v":"1896c681e572aecb"},"sqrtPrice":{"v":"17956c185245d62ef000"},"feeGrowthOutsideX":{"v":"029efb1aa549741d5191"},"feeGrowthOutsideY":{"v":"071c124329f1314620"},"secondsPerLiquidityOutside":{"v":"2818f2f7"},"secondsOutside":"44d724","bump":255},{"pool":{"_bn":"1570e38b95fe5780c18b5e5677a7bc7091fe4b9b678d511032b7f7ac2a7bd5c3"},"index":-40200,"sign":false,"liquidityChange":{"v":"17d344798f0cc0"},"liquidityGross":{"v":"17d344798f0cc0"},"sqrtPrice":{"v":"1c60454529aa647b9000"},"feeGrowthOutsideX":{"v":"00"},"feeGrowthOutsideY":{"v":"00"},"secondsPerLiquidityOutside":{"v":"00"},"secondsOutside":"00","bump":254},{"pool":{"_bn":"1570e38b95fe5780c18b5e5677a7bc7091fe4b9b678d511032b7f7ac2a7bd5c3"},"index":-47600,"sign":true,"liquidityChange":{"v":"17d344798f0cc0"},"liquidityGross":{"v":"17d344798f0cc0"},"sqrtPrice":{"v":"1399c61e8b740225b000"},"feeGrowthOutsideX":{"v":"2d24a4f3781bd3dfad"},"feeGrowthOutsideY":{"v":"751df97e2f614a30"},"secondsPerLiquidityOutside":{"v":"2c"},"secondsOutside":"14080d","bump":254},{"pool":{"_bn":"1570e38b95fe5780c18b5e5677a7bc7091fe4b9b678d511032b7f7ac2a7bd5c3"},"index":-43700,"sign":false,"liquidityChange":{"v":"1896c681e572aecb"},"liquidityGross":{"v":"1896c681e572aecb"},"sqrtPrice":{"v":"17d218a716af0f63f000"},"feeGrowthOutsideX":{"v":"00"},"feeGrowthOutsideY":{"v":"00"},"secondsPerLiquidityOutside":{"v":"00"},"secondsOutside":"00","bump":251}],"volumeX":"316524086500","volumeY":"3360875000"},{"timestamp":1660132800000,"ticks":[{"pool":{"_bn":"1570e38b95fe5780c18b5e5677a7bc7091fe4b9b678d511032b7f7ac2a7bd5c3"},"index":-43900,"sign":true,"liquidityChange":{"v":"1896c681e572aecb"},"liquidityGross":{"v":"1896c681e572aecb"},"sqrtPrice":{"v":"17956c185245d62ef000"},"feeGrowthOutsideX":{"v":"029efb1aa549741d5191"},"feeGrowthOutsideY":{"v":"071c124329f1314620"},"secondsPerLiquidityOutside":{"v":"2818f2f7"},"secondsOutside":"44d724","bump":255},{"pool":{"_bn":"1570e38b95fe5780c18b5e5677a7bc7091fe4b9b678d511032b7f7ac2a7bd5c3"},"index":-40200,"sign":false,"liquidityChange":{"v":"17d344798f0cc0"},"liquidityGross":{"v":"17d344798f0cc0"},"sqrtPrice":{"v":"1c60454529aa647b9000"},"feeGrowthOutsideX":{"v":"00"},"feeGrowthOutsideY":{"v":"00"},"secondsPerLiquidityOutside":{"v":"00"},"secondsOutside":"00","bump":254},{"pool":{"_bn":"1570e38b95fe5780c18b5e5677a7bc7091fe4b9b678d511032b7f7ac2a7bd5c3"},"index":-47600,"sign":true,"liquidityChange":{"v":"17d344798f0cc0"},"liquidityGross":{"v":"17d344798f0cc0"},"sqrtPrice":{"v":"1399c61e8b740225b000"},"feeGrowthOutsideX":{"v":"2d24a4f3781bd3dfad"},"feeGrowthOutsideY":{"v":"751df97e2f614a30"},"secondsPerLiquidityOutside":{"v":"2c"},"secondsOutside":"14080d","bump":254},{"pool":{"_bn":"1570e38b95fe5780c18b5e5677a7bc7091fe4b9b678d511032b7f7ac2a7bd5c3"},"index":-42800,"sign":false,"liquidityChange":{"v":"03111bd4fcff75"},"liquidityGross":{"v":"03111bd4fcff75"},"sqrtPrice":{"v":"18eac3a7390b98ee2000"},"feeGrowthOutsideX":{"v":"00"},"feeGrowthOutsideY":{"v":"00"},"secondsPerLiquidityOutside":{"v":"00"},"secondsOutside":"00","bump":251},{"pool":{"_bn":"1570e38b95fe5780c18b5e5677a7bc7091fe4b9b678d511032b7f7ac2a7bd5c3"},"index":-44800,"sign":true,"liquidityChange":{"v":"03111bd4fcff75"},"liquidityGross":{"v":"03111bd4fcff75"},"sqrtPrice":{"v":"168bc600cd8c58bcf000"},"feeGrowthOutsideX":{"v":"01e9f23258234723e0fe"},"feeGrowthOutsideY":{"v":"04f68728c83334dcfd"},"secondsPerLiquidityOutside":{"v":"28174a41"},"secondsOutside":"44d43c","bump":255},{"pool":{"_bn":"1570e38b95fe5780c18b5e5677a7bc7091fe4b9b678d511032b7f7ac2a7bd5c3"},"index":-43700,"sign":false,"liquidityChange":{"v":"1896c681e572aecb"},"liquidityGross":{"v":"1896c681e572aecb"},"sqrtPrice":{"v":"17d218a716af0f63f000"},"feeGrowthOutsideX":{"v":"00"},"feeGrowthOutsideY":{"v":"00"},"secondsPerLiquidityOutside":{"v":"00"},"secondsOutside":"00","bump":251}],"volumeX":"316524086500","volumeY":"3360875000"},{"timestamp":1660219200000,"ticks":[{"pool":{"_bn":"1570e38b95fe5780c18b5e5677a7bc7091fe4b9b678d511032b7f7ac2a7bd5c3"},"index":-43900,"sign":true,"liquidityChange":{"v":"1896c681e572aecb"},"liquidityGross":{"v":"1896c681e572aecb"},"sqrtPrice":{"v":"17956c185245d62ef000"},"feeGrowthOutsideX":{"v":"029efb1aa549741d5191"},"feeGrowthOutsideY":{"v":"071c124329f1314620"},"secondsPerLiquidityOutside":{"v":"2818f2f7"},"secondsOutside":"44d724","bump":255},{"pool":{"_bn":"1570e38b95fe5780c18b5e5677a7bc7091fe4b9b678d511032b7f7ac2a7bd5c3"},"index":-40200,"sign":false,"liquidityChange":{"v":"17d344798f0cc0"},"liquidityGross":{"v":"17d344798f0cc0"},"sqrtPrice":{"v":"1c60454529aa647b9000"},"feeGrowthOutsideX":{"v":"00"},"feeGrowthOutsideY":{"v":"00"},"secondsPerLiquidityOutside":{"v":"00"},"secondsOutside":"00","bump":254},{"pool":{"_bn":"1570e38b95fe5780c18b5e5677a7bc7091fe4b9b678d511032b7f7ac2a7bd5c3"},"index":-47600,"sign":true,"liquidityChange":{"v":"17d344798f0cc0"},"liquidityGross":{"v":"17d344798f0cc0"},"sqrtPrice":{"v":"1399c61e8b740225b000"},"feeGrowthOutsideX":{"v":"2d24a4f3781bd3dfad"},"feeGrowthOutsideY":{"v":"751df97e2f614a30"},"secondsPerLiquidityOutside":{"v":"2c"},"secondsOutside":"14080d","bump":254},{"pool":{"_bn":"1570e38b95fe5780c18b5e5677a7bc7091fe4b9b678d511032b7f7ac2a7bd5c3"},"index":-42800,"sign":false,"liquidityChange":{"v":"03111bd4fcff75"},"liquidityGross":{"v":"03111bd4fcff75"},"sqrtPrice":{"v":"18eac3a7390b98ee2000"},"feeGrowthOutsideX":{"v":"00"},"feeGrowthOutsideY":{"v":"00"},"secondsPerLiquidityOutside":{"v":"00"},"secondsOutside":"00","bump":251},{"pool":{"_bn":"1570e38b95fe5780c18b5e5677a7bc7091fe4b9b678d511032b7f7ac2a7bd5c3"},"index":-44800,"sign":true,"liquidityChange":{"v":"03111bd4fcff75"},"liquidityGross":{"v":"03111bd4fcff75"},"sqrtPrice":{"v":"168bc600cd8c58bcf000"},"feeGrowthOutsideX":{"v":"01e9f23258234723e0fe"},"feeGrowthOutsideY":{"v":"04f68728c83334dcfd"},"secondsPerLiquidityOutside":{"v":"28174a41"},"secondsOutside":"44d43c","bump":255},{"pool":{"_bn":"1570e38b95fe5780c18b5e5677a7bc7091fe4b9b678d511032b7f7ac2a7bd5c3"},"index":-43700,"sign":false,"liquidityChange":{"v":"1896c681e572aecb"},"liquidityGross":{"v":"1896c681e572aecb"},"sqrtPrice":{"v":"17d218a716af0f63f000"},"feeGrowthOutsideX":{"v":"00"},"feeGrowthOutsideY":{"v":"00"},"secondsPerLiquidityOutside":{"v":"00"},"secondsOutside":"00","bump":251}],"volumeX":"316524086500","volumeY":"3360875000"},{"timestamp":1660305600000,"ticks":[{"pool":{"_bn":"1570e38b95fe5780c18b5e5677a7bc7091fe4b9b678d511032b7f7ac2a7bd5c3"},"index":-47600,"sign":true,"liquidityChange":{"v":"17d344798f0cc0"},"liquidityGross":{"v":"17d344798f0cc0"},"sqrtPrice":{"v":"1399c61e8b740225b000"},"feeGrowthOutsideX":{"v":"2d24a4f3781bd3dfad"},"feeGrowthOutsideY":{"v":"751df97e2f614a30"},"secondsPerLiquidityOutside":{"v":"2c"},"secondsOutside":"14080d","bump":254},{"pool":{"_bn":"1570e38b95fe5780c18b5e5677a7bc7091fe4b9b678d511032b7f7ac2a7bd5c3"},"index":-44800,"sign":true,"liquidityChange":{"v":"03111bd4fcff75"},"liquidityGross":{"v":"03111bd4fcff75"},"sqrtPrice":{"v":"168bc600cd8c58bcf000"},"feeGrowthOutsideX":{"v":"01e9f23258234723e0fe"},"feeGrowthOutsideY":{"v":"04f68728c83334dcfd"},"secondsPerLiquidityOutside":{"v":"28174a41"},"secondsOutside":"44d43c","bump":255},{"pool":{"_bn":"1570e38b95fe5780c18b5e5677a7bc7091fe4b9b678d511032b7f7ac2a7bd5c3"},"index":-40200,"sign":false,"liquidityChange":{"v":"17d344798f0cc0"},"liquidityGross":{"v":"17d344798f0cc0"},"sqrtPrice":{"v":"1c60454529aa647b9000"},"feeGrowthOutsideX":{"v":"00"},"feeGrowthOutsideY":{"v":"00"},"secondsPerLiquidityOutside":{"v":"00"},"secondsOutside":"00","bump":254},{"pool":{"_bn":"1570e38b95fe5780c18b5e5677a7bc7091fe4b9b678d511032b7f7ac2a7bd5c3"},"index":-43700,"sign":false,"liquidityChange":{"v":"1896c681e572aecb"},"liquidityGross":{"v":"1896c681e572aecb"},"sqrtPrice":{"v":"17d218a716af0f63f000"},"feeGrowthOutsideX":{"v":"00"},"feeGrowthOutsideY":{"v":"00"},"secondsPerLiquidityOutside":{"v":"00"},"secondsOutside":"00","bump":251},{"pool":{"_bn":"1570e38b95fe5780c18b5e5677a7bc7091fe4b9b678d511032b7f7ac2a7bd5c3"},"index":-43900,"sign":true,"liquidityChange":{"v":"1896c681e572aecb"},"liquidityGross":{"v":"1896c681e572aecb"},"sqrtPrice":{"v":"17956c185245d62ef000"},"feeGrowthOutsideX":{"v":"029efb1aa549741d5191"},"feeGrowthOutsideY":{"v":"071c124329f1314620"},"secondsPerLiquidityOutside":{"v":"2818f2f7"},"secondsOutside":"44d724","bump":255},{"pool":{"_bn":"1570e38b95fe5780c18b5e5677a7bc7091fe4b9b678d511032b7f7ac2a7bd5c3"},"index":-42800,"sign":false,"liquidityChange":{"v":"03111bd4fcff75"},"liquidityGross":{"v":"03111bd4fcff75"},"sqrtPrice":{"v":"18eac3a7390b98ee2000"},"feeGrowthOutsideX":{"v":"00"},"feeGrowthOutsideY":{"v":"00"},"secondsPerLiquidityOutside":{"v":"00"},"secondsOutside":"00","bump":251}],"volumeX":"316524086500","volumeY":"3360875000"},{"timestamp":1660392000000,"ticks":[{"pool":{"_bn":"1570e38b95fe5780c18b5e5677a7bc7091fe4b9b678d511032b7f7ac2a7bd5c3"},"index":-43900,"sign":true,"liquidityChange":{"v":"1896c681e572aecb"},"liquidityGross":{"v":"1896c681e572aecb"},"sqrtPrice":{"v":"17956c185245d62ef000"},"feeGrowthOutsideX":{"v":"029efb1aa549741d5191"},"feeGrowthOutsideY":{"v":"071c124329f1314620"},"secondsPerLiquidityOutside":{"v":"2818f2f7"},"secondsOutside":"44d724","bump":255},{"pool":{"_bn":"1570e38b95fe5780c18b5e5677a7bc7091fe4b9b678d511032b7f7ac2a7bd5c3"},"index":-40200,"sign":false,"liquidityChange":{"v":"17d344798f0cc0"},"liquidityGross":{"v":"17d344798f0cc0"},"sqrtPrice":{"v":"1c60454529aa647b9000"},"feeGrowthOutsideX":{"v":"00"},"feeGrowthOutsideY":{"v":"00"},"secondsPerLiquidityOutside":{"v":"00"},"secondsOutside":"00","bump":254},{"pool":{"_bn":"1570e38b95fe5780c18b5e5677a7bc7091fe4b9b678d511032b7f7ac2a7bd5c3"},"index":-47600,"sign":true,"liquidityChange":{"v":"17d344798f0cc0"},"liquidityGross":{"v":"17d344798f0cc0"},"sqrtPrice":{"v":"1399c61e8b740225b000"},"feeGrowthOutsideX":{"v":"2d24a4f3781bd3dfad"},"feeGrowthOutsideY":{"v":"751df97e2f614a30"},"secondsPerLiquidityOutside":{"v":"2c"},"secondsOutside":"14080d","bump":254},{"pool":{"_bn":"1570e38b95fe5780c18b5e5677a7bc7091fe4b9b678d511032b7f7ac2a7bd5c3"},"index":-42800,"sign":false,"liquidityChange":{"v":"03111bd4fcff75"},"liquidityGross":{"v":"03111bd4fcff75"},"sqrtPrice":{"v":"18eac3a7390b98ee2000"},"feeGrowthOutsideX":{"v":"00"},"feeGrowthOutsideY":{"v":"00"},"secondsPerLiquidityOutside":{"v":"00"},"secondsOutside":"00","bump":251},{"pool":{"_bn":"1570e38b95fe5780c18b5e5677a7bc7091fe4b9b678d511032b7f7ac2a7bd5c3"},"index":-44800,"sign":true,"liquidityChange":{"v":"03111bd4fcff75"},"liquidityGross":{"v":"03111bd4fcff75"},"sqrtPrice":{"v":"168bc600cd8c58bcf000"},"feeGrowthOutsideX":{"v":"01e9f23258234723e0fe"},"feeGrowthOutsideY":{"v":"04f68728c83334dcfd"},"secondsPerLiquidityOutside":{"v":"28174a41"},"secondsOutside":"44d43c","bump":255},{"pool":{"_bn":"1570e38b95fe5780c18b5e5677a7bc7091fe4b9b678d511032b7f7ac2a7bd5c3"},"index":-43700,"sign":false,"liquidityChange":{"v":"1896c681e572aecb"},"liquidityGross":{"v":"1896c681e572aecb"},"sqrtPrice":{"v":"17d218a716af0f63f000"},"feeGrowthOutsideX":{"v":"00"},"feeGrowthOutsideY":{"v":"00"},"secondsPerLiquidityOutside":{"v":"00"},"secondsOutside":"00","bump":251}],"volumeX":"316524086500","volumeY":"3360875000"},{"timestamp":1660478400000,"ticks":[{"pool":{"_bn":"1570e38b95fe5780c18b5e5677a7bc7091fe4b9b678d511032b7f7ac2a7bd5c3"},"index":-43900,"sign":true,"liquidityChange":{"v":"1896c681e572aecb"},"liquidityGross":{"v":"1896c681e572aecb"},"sqrtPrice":{"v":"17956c185245d62ef000"},"feeGrowthOutsideX":{"v":"029efb1aa549741d5191"},"feeGrowthOutsideY":{"v":"071c124329f1314620"},"secondsPerLiquidityOutside":{"v":"2818f2f7"},"secondsOutside":"44d724","bump":255},{"pool":{"_bn":"1570e38b95fe5780c18b5e5677a7bc7091fe4b9b678d511032b7f7ac2a7bd5c3"},"index":-40200,"sign":false,"liquidityChange":{"v":"17d344798f0cc0"},"liquidityGross":{"v":"17d344798f0cc0"},"sqrtPrice":{"v":"1c60454529aa647b9000"},"feeGrowthOutsideX":{"v":"00"},"feeGrowthOutsideY":{"v":"00"},"secondsPerLiquidityOutside":{"v":"00"},"secondsOutside":"00","bump":254},{"pool":{"_bn":"1570e38b95fe5780c18b5e5677a7bc7091fe4b9b678d511032b7f7ac2a7bd5c3"},"index":-47600,"sign":true,"liquidityChange":{"v":"17d344798f0cc0"},"liquidityGross":{"v":"17d344798f0cc0"},"sqrtPrice":{"v":"1399c61e8b740225b000"},"feeGrowthOutsideX":{"v":"2d24a4f3781bd3dfad"},"feeGrowthOutsideY":{"v":"751df97e2f614a30"},"secondsPerLiquidityOutside":{"v":"2c"},"secondsOutside":"14080d","bump":254},{"pool":{"_bn":"1570e38b95fe5780c18b5e5677a7bc7091fe4b9b678d511032b7f7ac2a7bd5c3"},"index":-42800,"sign":false,"liquidityChange":{"v":"03111bd4fcff75"},"liquidityGross":{"v":"03111bd4fcff75"},"sqrtPrice":{"v":"18eac3a7390b98ee2000"},"feeGrowthOutsideX":{"v":"00"},"feeGrowthOutsideY":{"v":"00"},"secondsPerLiquidityOutside":{"v":"00"},"secondsOutside":"00","bump":251},{"pool":{"_bn":"1570e38b95fe5780c18b5e5677a7bc7091fe4b9b678d511032b7f7ac2a7bd5c3"},"index":-44800,"sign":true,"liquidityChange":{"v":"03111bd4fcff75"},"liquidityGross":{"v":"03111bd4fcff75"},"sqrtPrice":{"v":"168bc600cd8c58bcf000"},"feeGrowthOutsideX":{"v":"01e9f23258234723e0fe"},"feeGrowthOutsideY":{"v":"04f68728c83334dcfd"},"secondsPerLiquidityOutside":{"v":"28174a41"},"secondsOutside":"44d43c","bump":255},{"pool":{"_bn":"1570e38b95fe5780c18b5e5677a7bc7091fe4b9b678d511032b7f7ac2a7bd5c3"},"index":-43700,"sign":false,"liquidityChange":{"v":"1896c681e572aecb"},"liquidityGross":{"v":"1896c681e572aecb"},"sqrtPrice":{"v":"17d218a716af0f63f000"},"feeGrowthOutsideX":{"v":"00"},"feeGrowthOutsideY":{"v":"00"},"secondsPerLiquidityOutside":{"v":"00"},"secondsOutside":"00","bump":251}],"volumeX":"316524086500","volumeY":"3360875000"},{"timestamp":1660564800000,"ticks":[{"pool":{"_bn":"1570e38b95fe5780c18b5e5677a7bc7091fe4b9b678d511032b7f7ac2a7bd5c3"},"index":-47600,"sign":true,"liquidityChange":{"v":"17d344798f0cc0"},"liquidityGross":{"v":"17d344798f0cc0"},"sqrtPrice":{"v":"1399c61e8b740225b000"},"feeGrowthOutsideX":{"v":"2d24a4f3781bd3dfad"},"feeGrowthOutsideY":{"v":"751df97e2f614a30"},"secondsPerLiquidityOutside":{"v":"2c"},"secondsOutside":"14080d","bump":254},{"pool":{"_bn":"1570e38b95fe5780c18b5e5677a7bc7091fe4b9b678d511032b7f7ac2a7bd5c3"},"index":-44800,"sign":true,"liquidityChange":{"v":"03111bd4fcff75"},"liquidityGross":{"v":"03111bd4fcff75"},"sqrtPrice":{"v":"168bc600cd8c58bcf000"},"feeGrowthOutsideX":{"v":"01e9f23258234723e0fe"},"feeGrowthOutsideY":{"v":"04f68728c83334dcfd"},"secondsPerLiquidityOutside":{"v":"28174a41"},"secondsOutside":"44d43c","bump":255},{"pool":{"_bn":"1570e38b95fe5780c18b5e5677a7bc7091fe4b9b678d511032b7f7ac2a7bd5c3"},"index":-40200,"sign":false,"liquidityChange":{"v":"17d344798f0cc0"},"liquidityGross":{"v":"17d344798f0cc0"},"sqrtPrice":{"v":"1c60454529aa647b9000"},"feeGrowthOutsideX":{"v":"00"},"feeGrowthOutsideY":{"v":"00"},"secondsPerLiquidityOutside":{"v":"00"},"secondsOutside":"00","bump":254},{"pool":{"_bn":"1570e38b95fe5780c18b5e5677a7bc7091fe4b9b678d511032b7f7ac2a7bd5c3"},"index":-43700,"sign":false,"liquidityChange":{"v":"1896c681e572aecb"},"liquidityGross":{"v":"1896c681e572aecb"},"sqrtPrice":{"v":"17d218a716af0f63f000"},"feeGrowthOutsideX":{"v":"00"},"feeGrowthOutsideY":{"v":"00"},"secondsPerLiquidityOutside":{"v":"00"},"secondsOutside":"00","bump":251},{"pool":{"_bn":"1570e38b95fe5780c18b5e5677a7bc7091fe4b9b678d511032b7f7ac2a7bd5c3"},"index":-43900,"sign":true,"liquidityChange":{"v":"1896c681e572aecb"},"liquidityGross":{"v":"1896c681e572aecb"},"sqrtPrice":{"v":"17956c185245d62ef000"},"feeGrowthOutsideX":{"v":"029efb1aa549741d5191"},"feeGrowthOutsideY":{"v":"071c124329f1314620"},"secondsPerLiquidityOutside":{"v":"2818f2f7"},"secondsOutside":"44d724","bump":255},{"pool":{"_bn":"1570e38b95fe5780c18b5e5677a7bc7091fe4b9b678d511032b7f7ac2a7bd5c3"},"index":-42800,"sign":false,"liquidityChange":{"v":"03111bd4fcff75"},"liquidityGross":{"v":"03111bd4fcff75"},"sqrtPrice":{"v":"18eac3a7390b98ee2000"},"feeGrowthOutsideX":{"v":"00"},"feeGrowthOutsideY":{"v":"00"},"secondsPerLiquidityOutside":{"v":"00"},"secondsOutside":"00","bump":251}],"volumeX":"316524086500","volumeY":"3360875000"},{"timestamp":1660651200000,"ticks":[{"pool":{"_bn":"1570e38b95fe5780c18b5e5677a7bc7091fe4b9b678d511032b7f7ac2a7bd5c3"},"index":-42800,"sign":false,"liquidityChange":{"v":"03111bd4fcff75"},"liquidityGross":{"v":"03111bd4fcff75"},"sqrtPrice":{"v":"18eac3a7390b98ee2000"},"feeGrowthOutsideX":{"v":"00"},"feeGrowthOutsideY":{"v":"00"},"secondsPerLiquidityOutside":{"v":"00"},"secondsOutside":"00","bump":251},{"pool":{"_bn":"1570e38b95fe5780c18b5e5677a7bc7091fe4b9b678d511032b7f7ac2a7bd5c3"},"index":-44800,"sign":true,"liquidityChange":{"v":"03111bd4fcff75"},"liquidityGross":{"v":"03111bd4fcff75"},"sqrtPrice":{"v":"168bc600cd8c58bcf000"},"feeGrowthOutsideX":{"v":"01e9f23258234723e0fe"},"feeGrowthOutsideY":{"v":"04f68728c83334dcfd"},"secondsPerLiquidityOutside":{"v":"28174a41"},"secondsOutside":"44d43c","bump":255},{"pool":{"_bn":"1570e38b95fe5780c18b5e5677a7bc7091fe4b9b678d511032b7f7ac2a7bd5c3"},"index":-43900,"sign":true,"liquidityChange":{"v":"1896c681e572aecb"},"liquidityGross":{"v":"1896c681e572aecb"},"sqrtPrice":{"v":"17956c185245d62ef000"},"feeGrowthOutsideX":{"v":"029efb1aa549741d5191"},"feeGrowthOutsideY":{"v":"071c124329f1314620"},"secondsPerLiquidityOutside":{"v":"2818f2f7"},"secondsOutside":"44d724","bump":255},{"pool":{"_bn":"1570e38b95fe5780c18b5e5677a7bc7091fe4b9b678d511032b7f7ac2a7bd5c3"},"index":-40200,"sign":false,"liquidityChange":{"v":"17d344798f0cc0"},"liquidityGross":{"v":"17d344798f0cc0"},"sqrtPrice":{"v":"1c60454529aa647b9000"},"feeGrowthOutsideX":{"v":"00"},"feeGrowthOutsideY":{"v":"00"},"secondsPerLiquidityOutside":{"v":"00"},"secondsOutside":"00","bump":254},{"pool":{"_bn":"1570e38b95fe5780c18b5e5677a7bc7091fe4b9b678d511032b7f7ac2a7bd5c3"},"index":-47600,"sign":true,"liquidityChange":{"v":"17d344798f0cc0"},"liquidityGross":{"v":"17d344798f0cc0"},"sqrtPrice":{"v":"1399c61e8b740225b000"},"feeGrowthOutsideX":{"v":"2d24a4f3781bd3dfad"},"feeGrowthOutsideY":{"v":"751df97e2f614a30"},"secondsPerLiquidityOutside":{"v":"2c"},"secondsOutside":"14080d","bump":254},{"pool":{"_bn":"1570e38b95fe5780c18b5e5677a7bc7091fe4b9b678d511032b7f7ac2a7bd5c3"},"index":-43700,"sign":false,"liquidityChange":{"v":"1896c681e572aecb"},"liquidityGross":{"v":"1896c681e572aecb"},"sqrtPrice":{"v":"17d218a716af0f63f000"},"feeGrowthOutsideX":{"v":"00"},"feeGrowthOutsideY":{"v":"00"},"secondsPerLiquidityOutside":{"v":"00"},"secondsOutside":"00","bump":251}],"volumeX":"316524086500","volumeY":"3360875000"},{"timestamp":1660737600000,"ticks":[{"pool":{"_bn":"1570e38b95fe5780c18b5e5677a7bc7091fe4b9b678d511032b7f7ac2a7bd5c3"},"index":-43900,"sign":true,"liquidityChange":{"v":"1896c681e572aecb"},"liquidityGross":{"v":"1896c681e572aecb"},"sqrtPrice":{"v":"17956c185245d62ef000"},"feeGrowthOutsideX":{"v":"029efb1aa549741d5191"},"feeGrowthOutsideY":{"v":"071c124329f1314620"},"secondsPerLiquidityOutside":{"v":"2818f2f7"},"secondsOutside":"44d724","bump":255},{"pool":{"_bn":"1570e38b95fe5780c18b5e5677a7bc7091fe4b9b678d511032b7f7ac2a7bd5c3"},"index":-40200,"sign":false,"liquidityChange":{"v":"17d344798f0cc0"},"liquidityGross":{"v":"17d344798f0cc0"},"sqrtPrice":{"v":"1c60454529aa647b9000"},"feeGrowthOutsideX":{"v":"00"},"feeGrowthOutsideY":{"v":"00"},"secondsPerLiquidityOutside":{"v":"00"},"secondsOutside":"00","bump":254},{"pool":{"_bn":"1570e38b95fe5780c18b5e5677a7bc7091fe4b9b678d511032b7f7ac2a7bd5c3"},"index":-47600,"sign":true,"liquidityChange":{"v":"17d344798f0cc0"},"liquidityGross":{"v":"17d344798f0cc0"},"sqrtPrice":{"v":"1399c61e8b740225b000"},"feeGrowthOutsideX":{"v":"2d24a4f3781bd3dfad"},"feeGrowthOutsideY":{"v":"751df97e2f614a30"},"secondsPerLiquidityOutside":{"v":"2c"},"secondsOutside":"14080d","bump":254},{"pool":{"_bn":"1570e38b95fe5780c18b5e5677a7bc7091fe4b9b678d511032b7f7ac2a7bd5c3"},"index":-42800,"sign":false,"liquidityChange":{"v":"03111bd4fcff75"},"liquidityGross":{"v":"03111bd4fcff75"},"sqrtPrice":{"v":"18eac3a7390b98ee2000"},"feeGrowthOutsideX":{"v":"00"},"feeGrowthOutsideY":{"v":"00"},"secondsPerLiquidityOutside":{"v":"00"},"secondsOutside":"00","bump":251},{"pool":{"_bn":"1570e38b95fe5780c18b5e5677a7bc7091fe4b9b678d511032b7f7ac2a7bd5c3"},"index":-44800,"sign":true,"liquidityChange":{"v":"03111bd4fcff75"},"liquidityGross":{"v":"03111bd4fcff75"},"sqrtPrice":{"v":"168bc600cd8c58bcf000"},"feeGrowthOutsideX":{"v":"01e9f23258234723e0fe"},"feeGrowthOutsideY":{"v":"04f68728c83334dcfd"},"secondsPerLiquidityOutside":{"v":"28174a41"},"secondsOutside":"44d43c","bump":255},{"pool":{"_bn":"1570e38b95fe5780c18b5e5677a7bc7091fe4b9b678d511032b7f7ac2a7bd5c3"},"index":-43700,"sign":false,"liquidityChange":{"v":"1896c681e572aecb"},"liquidityGross":{"v":"1896c681e572aecb"},"sqrtPrice":{"v":"17d218a716af0f63f000"},"feeGrowthOutsideX":{"v":"00"},"feeGrowthOutsideY":{"v":"00"},"secondsPerLiquidityOutside":{"v":"00"},"secondsOutside":"00","bump":251}],"volumeX":"316524086500","volumeY":"3360875000"},{"timestamp":1660824000000,"ticks":[{"pool":{"_bn":"1570e38b95fe5780c18b5e5677a7bc7091fe4b9b678d511032b7f7ac2a7bd5c3"},"index":-43900,"sign":true,"liquidityChange":{"v":"1896c681e572aecb"},"liquidityGross":{"v":"1896c681e572aecb"},"sqrtPrice":{"v":"17956c185245d62ef000"},"feeGrowthOutsideX":{"v":"029efb1aa549741d5191"},"feeGrowthOutsideY":{"v":"071c124329f1314620"},"secondsPerLiquidityOutside":{"v":"2818f2f7"},"secondsOutside":"44d724","bump":255},{"pool":{"_bn":"1570e38b95fe5780c18b5e5677a7bc7091fe4b9b678d511032b7f7ac2a7bd5c3"},"index":-40200,"sign":false,"liquidityChange":{"v":"17d344798f0cc0"},"liquidityGross":{"v":"17d344798f0cc0"},"sqrtPrice":{"v":"1c60454529aa647b9000"},"feeGrowthOutsideX":{"v":"00"},"feeGrowthOutsideY":{"v":"00"},"secondsPerLiquidityOutside":{"v":"00"},"secondsOutside":"00","bump":254},{"pool":{"_bn":"1570e38b95fe5780c18b5e5677a7bc7091fe4b9b678d511032b7f7ac2a7bd5c3"},"index":-47600,"sign":true,"liquidityChange":{"v":"17d344798f0cc0"},"liquidityGross":{"v":"17d344798f0cc0"},"sqrtPrice":{"v":"1399c61e8b740225b000"},"feeGrowthOutsideX":{"v":"2d24a4f3781bd3dfad"},"feeGrowthOutsideY":{"v":"751df97e2f614a30"},"secondsPerLiquidityOutside":{"v":"2c"},"secondsOutside":"14080d","bump":254},{"pool":{"_bn":"1570e38b95fe5780c18b5e5677a7bc7091fe4b9b678d511032b7f7ac2a7bd5c3"},"index":-42800,"sign":false,"liquidityChange":{"v":"03111bd4fcff75"},"liquidityGross":{"v":"03111bd4fcff75"},"sqrtPrice":{"v":"18eac3a7390b98ee2000"},"feeGrowthOutsideX":{"v":"00"},"feeGrowthOutsideY":{"v":"00"},"secondsPerLiquidityOutside":{"v":"00"},"secondsOutside":"00","bump":251},{"pool":{"_bn":"1570e38b95fe5780c18b5e5677a7bc7091fe4b9b678d511032b7f7ac2a7bd5c3"},"index":-44800,"sign":true,"liquidityChange":{"v":"03111bd4fcff75"},"liquidityGross":{"v":"03111bd4fcff75"},"sqrtPrice":{"v":"168bc600cd8c58bcf000"},"feeGrowthOutsideX":{"v":"01e9f23258234723e0fe"},"feeGrowthOutsideY":{"v":"04f68728c83334dcfd"},"secondsPerLiquidityOutside":{"v":"28174a41"},"secondsOutside":"44d43c","bump":255},{"pool":{"_bn":"1570e38b95fe5780c18b5e5677a7bc7091fe4b9b678d511032b7f7ac2a7bd5c3"},"index":-43700,"sign":false,"liquidityChange":{"v":"1896c681e572aecb"},"liquidityGross":{"v":"1896c681e572aecb"},"sqrtPrice":{"v":"17d218a716af0f63f000"},"feeGrowthOutsideX":{"v":"00"},"feeGrowthOutsideY":{"v":"00"},"secondsPerLiquidityOutside":{"v":"00"},"secondsOutside":"00","bump":251}],"volumeX":"316524086500","volumeY":"3360875000"},{"timestamp":1660910400000,"ticks":[{"pool":{"_bn":"1570e38b95fe5780c18b5e5677a7bc7091fe4b9b678d511032b7f7ac2a7bd5c3"},"index":-42800,"sign":false,"liquidityChange":{"v":"03111bd4fcff75"},"liquidityGross":{"v":"03111bd4fcff75"},"sqrtPrice":{"v":"18eac3a7390b98ee2000"},"feeGrowthOutsideX":{"v":"00"},"feeGrowthOutsideY":{"v":"00"},"secondsPerLiquidityOutside":{"v":"00"},"secondsOutside":"00","bump":251},{"pool":{"_bn":"1570e38b95fe5780c18b5e5677a7bc7091fe4b9b678d511032b7f7ac2a7bd5c3"},"index":-44800,"sign":true,"liquidityChange":{"v":"03111bd4fcff75"},"liquidityGross":{"v":"03111bd4fcff75"},"sqrtPrice":{"v":"168bc600cd8c58bcf000"},"feeGrowthOutsideX":{"v":"01e9f23258234723e0fe"},"feeGrowthOutsideY":{"v":"04f68728c83334dcfd"},"secondsPerLiquidityOutside":{"v":"28174a41"},"secondsOutside":"44d43c","bump":255},{"pool":{"_bn":"1570e38b95fe5780c18b5e5677a7bc7091fe4b9b678d511032b7f7ac2a7bd5c3"},"index":-43900,"sign":true,"liquidityChange":{"v":"1896c681e572aecb"},"liquidityGross":{"v":"1896c681e572aecb"},"sqrtPrice":{"v":"17956c185245d62ef000"},"feeGrowthOutsideX":{"v":"029efb1aa549741d5191"},"feeGrowthOutsideY":{"v":"071c124329f1314620"},"secondsPerLiquidityOutside":{"v":"2818f2f7"},"secondsOutside":"44d724","bump":255},{"pool":{"_bn":"1570e38b95fe5780c18b5e5677a7bc7091fe4b9b678d511032b7f7ac2a7bd5c3"},"index":-40200,"sign":false,"liquidityChange":{"v":"17d344798f0cc0"},"liquidityGross":{"v":"17d344798f0cc0"},"sqrtPrice":{"v":"1c60454529aa647b9000"},"feeGrowthOutsideX":{"v":"00"},"feeGrowthOutsideY":{"v":"00"},"secondsPerLiquidityOutside":{"v":"00"},"secondsOutside":"00","bump":254},{"pool":{"_bn":"1570e38b95fe5780c18b5e5677a7bc7091fe4b9b678d511032b7f7ac2a7bd5c3"},"index":-47600,"sign":true,"liquidityChange":{"v":"17d344798f0cc0"},"liquidityGross":{"v":"17d344798f0cc0"},"sqrtPrice":{"v":"1399c61e8b740225b000"},"feeGrowthOutsideX":{"v":"2d24a4f3781bd3dfad"},"feeGrowthOutsideY":{"v":"751df97e2f614a30"},"secondsPerLiquidityOutside":{"v":"2c"},"secondsOutside":"14080d","bump":254},{"pool":{"_bn":"1570e38b95fe5780c18b5e5677a7bc7091fe4b9b678d511032b7f7ac2a7bd5c3"},"index":-43700,"sign":false,"liquidityChange":{"v":"1896c681e572aecb"},"liquidityGross":{"v":"1896c681e572aecb"},"sqrtPrice":{"v":"17d218a716af0f63f000"},"feeGrowthOutsideX":{"v":"00"},"feeGrowthOutsideY":{"v":"00"},"secondsPerLiquidityOutside":{"v":"00"},"secondsOutside":"00","bump":251}],"volumeX":"316524086500","volumeY":"3360875000"},{"timestamp":1660996800000,"ticks":[{"pool":{"_bn":"1570e38b95fe5780c18b5e5677a7bc7091fe4b9b678d511032b7f7ac2a7bd5c3"},"index":-47600,"sign":true,"liquidityChange":{"v":"17d344798f0cc0"},"liquidityGross":{"v":"17d344798f0cc0"},"sqrtPrice":{"v":"1399c61e8b740225b000"},"feeGrowthOutsideX":{"v":"2d24a4f3781bd3dfad"},"feeGrowthOutsideY":{"v":"751df97e2f614a30"},"secondsPerLiquidityOutside":{"v":"2c"},"secondsOutside":"14080d","bump":254},{"pool":{"_bn":"1570e38b95fe5780c18b5e5677a7bc7091fe4b9b678d511032b7f7ac2a7bd5c3"},"index":-44800,"sign":true,"liquidityChange":{"v":"03111bd4fcff75"},"liquidityGross":{"v":"03111bd4fcff75"},"sqrtPrice":{"v":"168bc600cd8c58bcf000"},"feeGrowthOutsideX":{"v":"01e9f23258234723e0fe"},"feeGrowthOutsideY":{"v":"04f68728c83334dcfd"},"secondsPerLiquidityOutside":{"v":"28174a41"},"secondsOutside":"44d43c","bump":255},{"pool":{"_bn":"1570e38b95fe5780c18b5e5677a7bc7091fe4b9b678d511032b7f7ac2a7bd5c3"},"index":-40200,"sign":false,"liquidityChange":{"v":"17d344798f0cc0"},"liquidityGross":{"v":"17d344798f0cc0"},"sqrtPrice":{"v":"1c60454529aa647b9000"},"feeGrowthOutsideX":{"v":"00"},"feeGrowthOutsideY":{"v":"00"},"secondsPerLiquidityOutside":{"v":"00"},"secondsOutside":"00","bump":254},{"pool":{"_bn":"1570e38b95fe5780c18b5e5677a7bc7091fe4b9b678d511032b7f7ac2a7bd5c3"},"index":-43700,"sign":false,"liquidityChange":{"v":"1896c681e572aecb"},"liquidityGross":{"v":"1896c681e572aecb"},"sqrtPrice":{"v":"17d218a716af0f63f000"},"feeGrowthOutsideX":{"v":"00"},"feeGrowthOutsideY":{"v":"00"},"secondsPerLiquidityOutside":{"v":"00"},"secondsOutside":"00","bump":251},{"pool":{"_bn":"1570e38b95fe5780c18b5e5677a7bc7091fe4b9b678d511032b7f7ac2a7bd5c3"},"index":-43900,"sign":true,"liquidityChange":{"v":"1896c681e572aecb"},"liquidityGross":{"v":"1896c681e572aecb"},"sqrtPrice":{"v":"17956c185245d62ef000"},"feeGrowthOutsideX":{"v":"029efb1aa549741d5191"},"feeGrowthOutsideY":{"v":"071c124329f1314620"},"secondsPerLiquidityOutside":{"v":"2818f2f7"},"secondsOutside":"44d724","bump":255},{"pool":{"_bn":"1570e38b95fe5780c18b5e5677a7bc7091fe4b9b678d511032b7f7ac2a7bd5c3"},"index":-42800,"sign":false,"liquidityChange":{"v":"03111bd4fcff75"},"liquidityGross":{"v":"03111bd4fcff75"},"sqrtPrice":{"v":"18eac3a7390b98ee2000"},"feeGrowthOutsideX":{"v":"00"},"feeGrowthOutsideY":{"v":"00"},"secondsPerLiquidityOutside":{"v":"00"},"secondsOutside":"00","bump":251}],"volumeX":"316524086500","volumeY":"3360875000"},{"timestamp":1661083200000,"ticks":[{"pool":{"_bn":"1570e38b95fe5780c18b5e5677a7bc7091fe4b9b678d511032b7f7ac2a7bd5c3"},"index":-47600,"sign":true,"liquidityChange":{"v":"17d344798f0cc0"},"liquidityGross":{"v":"17d344798f0cc0"},"sqrtPrice":{"v":"1399c61e8b740225b000"},"feeGrowthOutsideX":{"v":"2d24a4f3781bd3dfad"},"feeGrowthOutsideY":{"v":"751df97e2f614a30"},"secondsPerLiquidityOutside":{"v":"2c"},"secondsOutside":"14080d","bump":254},{"pool":{"_bn":"1570e38b95fe5780c18b5e5677a7bc7091fe4b9b678d511032b7f7ac2a7bd5c3"},"index":-44800,"sign":true,"liquidityChange":{"v":"03111bd4fcff75"},"liquidityGross":{"v":"03111bd4fcff75"},"sqrtPrice":{"v":"168bc600cd8c58bcf000"},"feeGrowthOutsideX":{"v":"01e9f23258234723e0fe"},"feeGrowthOutsideY":{"v":"04f68728c83334dcfd"},"secondsPerLiquidityOutside":{"v":"28174a41"},"secondsOutside":"44d43c","bump":255},{"pool":{"_bn":"1570e38b95fe5780c18b5e5677a7bc7091fe4b9b678d511032b7f7ac2a7bd5c3"},"index":-40200,"sign":false,"liquidityChange":{"v":"17d344798f0cc0"},"liquidityGross":{"v":"17d344798f0cc0"},"sqrtPrice":{"v":"1c60454529aa647b9000"},"feeGrowthOutsideX":{"v":"00"},"feeGrowthOutsideY":{"v":"00"},"secondsPerLiquidityOutside":{"v":"00"},"secondsOutside":"00","bump":254},{"pool":{"_bn":"1570e38b95fe5780c18b5e5677a7bc7091fe4b9b678d511032b7f7ac2a7bd5c3"},"index":-43700,"sign":false,"liquidityChange":{"v":"1896c681e572aecb"},"liquidityGross":{"v":"1896c681e572aecb"},"sqrtPrice":{"v":"17d218a716af0f63f000"},"feeGrowthOutsideX":{"v":"00"},"feeGrowthOutsideY":{"v":"00"},"secondsPerLiquidityOutside":{"v":"00"},"secondsOutside":"00","bump":251},{"pool":{"_bn":"1570e38b95fe5780c18b5e5677a7bc7091fe4b9b678d511032b7f7ac2a7bd5c3"},"index":-43900,"sign":true,"liquidityChange":{"v":"1896c681e572aecb"},"liquidityGross":{"v":"1896c681e572aecb"},"sqrtPrice":{"v":"17956c185245d62ef000"},"feeGrowthOutsideX":{"v":"029efb1aa549741d5191"},"feeGrowthOutsideY":{"v":"071c124329f1314620"},"secondsPerLiquidityOutside":{"v":"2818f2f7"},"secondsOutside":"44d724","bump":255},{"pool":{"_bn":"1570e38b95fe5780c18b5e5677a7bc7091fe4b9b678d511032b7f7ac2a7bd5c3"},"index":-42800,"sign":false,"liquidityChange":{"v":"03111bd4fcff75"},"liquidityGross":{"v":"03111bd4fcff75"},"sqrtPrice":{"v":"18eac3a7390b98ee2000"},"feeGrowthOutsideX":{"v":"00"},"feeGrowthOutsideY":{"v":"00"},"secondsPerLiquidityOutside":{"v":"00"},"secondsOutside":"00","bump":251}],"volumeX":"316524086500","volumeY":"3360875000"},{"timestamp":1661169600000,"ticks":[{"pool":{"_bn":"1570e38b95fe5780c18b5e5677a7bc7091fe4b9b678d511032b7f7ac2a7bd5c3"},"index":-42800,"sign":false,"liquidityChange":{"v":"03111bd4fcff75"},"liquidityGross":{"v":"03111bd4fcff75"},"sqrtPrice":{"v":"18eac3a7390b98ee2000"},"feeGrowthOutsideX":{"v":"00"},"feeGrowthOutsideY":{"v":"00"},"secondsPerLiquidityOutside":{"v":"00"},"secondsOutside":"00","bump":251},{"pool":{"_bn":"1570e38b95fe5780c18b5e5677a7bc7091fe4b9b678d511032b7f7ac2a7bd5c3"},"index":-44800,"sign":true,"liquidityChange":{"v":"03111bd4fcff75"},"liquidityGross":{"v":"03111bd4fcff75"},"sqrtPrice":{"v":"168bc600cd8c58bcf000"},"feeGrowthOutsideX":{"v":"01e9f23258234723e0fe"},"feeGrowthOutsideY":{"v":"04f68728c83334dcfd"},"secondsPerLiquidityOutside":{"v":"28174a41"},"secondsOutside":"44d43c","bump":255},{"pool":{"_bn":"1570e38b95fe5780c18b5e5677a7bc7091fe4b9b678d511032b7f7ac2a7bd5c3"},"index":-43900,"sign":true,"liquidityChange":{"v":"1896c681e572aecb"},"liquidityGross":{"v":"1896c681e572aecb"},"sqrtPrice":{"v":"17956c185245d62ef000"},"feeGrowthOutsideX":{"v":"029efb1aa549741d5191"},"feeGrowthOutsideY":{"v":"071c124329f1314620"},"secondsPerLiquidityOutside":{"v":"2818f2f7"},"secondsOutside":"44d724","bump":255},{"pool":{"_bn":"1570e38b95fe5780c18b5e5677a7bc7091fe4b9b678d511032b7f7ac2a7bd5c3"},"index":-40200,"sign":false,"liquidityChange":{"v":"17d344798f0cc0"},"liquidityGross":{"v":"17d344798f0cc0"},"sqrtPrice":{"v":"1c60454529aa647b9000"},"feeGrowthOutsideX":{"v":"00"},"feeGrowthOutsideY":{"v":"00"},"secondsPerLiquidityOutside":{"v":"00"},"secondsOutside":"00","bump":254},{"pool":{"_bn":"1570e38b95fe5780c18b5e5677a7bc7091fe4b9b678d511032b7f7ac2a7bd5c3"},"index":-47600,"sign":true,"liquidityChange":{"v":"17d344798f0cc0"},"liquidityGross":{"v":"17d344798f0cc0"},"sqrtPrice":{"v":"1399c61e8b740225b000"},"feeGrowthOutsideX":{"v":"2d24a4f3781bd3dfad"},"feeGrowthOutsideY":{"v":"751df97e2f614a30"},"secondsPerLiquidityOutside":{"v":"2c"},"secondsOutside":"14080d","bump":254},{"pool":{"_bn":"1570e38b95fe5780c18b5e5677a7bc7091fe4b9b678d511032b7f7ac2a7bd5c3"},"index":-43700,"sign":false,"liquidityChange":{"v":"1896c681e572aecb"},"liquidityGross":{"v":"1896c681e572aecb"},"sqrtPrice":{"v":"17d218a716af0f63f000"},"feeGrowthOutsideX":{"v":"00"},"feeGrowthOutsideY":{"v":"00"},"secondsPerLiquidityOutside":{"v":"00"},"secondsOutside":"00","bump":251}],"volumeX":"316524086500","volumeY":"3360875000"},{"timestamp":1661256000000,"ticks":[{"pool":{"_bn":"1570e38b95fe5780c18b5e5677a7bc7091fe4b9b678d511032b7f7ac2a7bd5c3"},"index":-43900,"sign":true,"liquidityChange":{"v":"1896c681e572aecb"},"liquidityGross":{"v":"1896c681e572aecb"},"sqrtPrice":{"v":"17956c185245d62ef000"},"feeGrowthOutsideX":{"v":"029efb1aa549741d5191"},"feeGrowthOutsideY":{"v":"071c124329f1314620"},"secondsPerLiquidityOutside":{"v":"2818f2f7"},"secondsOutside":"44d724","bump":255},{"pool":{"_bn":"1570e38b95fe5780c18b5e5677a7bc7091fe4b9b678d511032b7f7ac2a7bd5c3"},"index":-40200,"sign":false,"liquidityChange":{"v":"17d344798f0cc0"},"liquidityGross":{"v":"17d344798f0cc0"},"sqrtPrice":{"v":"1c60454529aa647b9000"},"feeGrowthOutsideX":{"v":"00"},"feeGrowthOutsideY":{"v":"00"},"secondsPerLiquidityOutside":{"v":"00"},"secondsOutside":"00","bump":254},{"pool":{"_bn":"1570e38b95fe5780c18b5e5677a7bc7091fe4b9b678d511032b7f7ac2a7bd5c3"},"index":-47600,"sign":true,"liquidityChange":{"v":"17d344798f0cc0"},"liquidityGross":{"v":"17d344798f0cc0"},"sqrtPrice":{"v":"1399c61e8b740225b000"},"feeGrowthOutsideX":{"v":"2d24a4f3781bd3dfad"},"feeGrowthOutsideY":{"v":"751df97e2f614a30"},"secondsPerLiquidityOutside":{"v":"2c"},"secondsOutside":"14080d","bump":254},{"pool":{"_bn":"1570e38b95fe5780c18b5e5677a7bc7091fe4b9b678d511032b7f7ac2a7bd5c3"},"index":-42800,"sign":false,"liquidityChange":{"v":"03111bd4fcff75"},"liquidityGross":{"v":"03111bd4fcff75"},"sqrtPrice":{"v":"18eac3a7390b98ee2000"},"feeGrowthOutsideX":{"v":"00"},"feeGrowthOutsideY":{"v":"00"},"secondsPerLiquidityOutside":{"v":"00"},"secondsOutside":"00","bump":251},{"pool":{"_bn":"1570e38b95fe5780c18b5e5677a7bc7091fe4b9b678d511032b7f7ac2a7bd5c3"},"index":-44800,"sign":true,"liquidityChange":{"v":"03111bd4fcff75"},"liquidityGross":{"v":"03111bd4fcff75"},"sqrtPrice":{"v":"168bc600cd8c58bcf000"},"feeGrowthOutsideX":{"v":"01e9f23258234723e0fe"},"feeGrowthOutsideY":{"v":"04f68728c83334dcfd"},"secondsPerLiquidityOutside":{"v":"28174a41"},"secondsOutside":"44d43c","bump":255},{"pool":{"_bn":"1570e38b95fe5780c18b5e5677a7bc7091fe4b9b678d511032b7f7ac2a7bd5c3"},"index":-43700,"sign":false,"liquidityChange":{"v":"1896c681e572aecb"},"liquidityGross":{"v":"1896c681e572aecb"},"sqrtPrice":{"v":"17d218a716af0f63f000"},"feeGrowthOutsideX":{"v":"00"},"feeGrowthOutsideY":{"v":"00"},"secondsPerLiquidityOutside":{"v":"00"},"secondsOutside":"00","bump":251}],"volumeX":"316524086500","volumeY":"3360875000"},{"timestamp":1661342400000,"ticks":[{"pool":{"_bn":"1570e38b95fe5780c18b5e5677a7bc7091fe4b9b678d511032b7f7ac2a7bd5c3"},"index":-43900,"sign":true,"liquidityChange":{"v":"1896c681e572aecb"},"liquidityGross":{"v":"1896c681e572aecb"},"sqrtPrice":{"v":"17956c185245d62ef000"},"feeGrowthOutsideX":{"v":"029efb1aa549741d5191"},"feeGrowthOutsideY":{"v":"071c124329f1314620"},"secondsPerLiquidityOutside":{"v":"2818f2f7"},"secondsOutside":"44d724","bump":255},{"pool":{"_bn":"1570e38b95fe5780c18b5e5677a7bc7091fe4b9b678d511032b7f7ac2a7bd5c3"},"index":-40200,"sign":false,"liquidityChange":{"v":"17d344798f0cc0"},"liquidityGross":{"v":"17d344798f0cc0"},"sqrtPrice":{"v":"1c60454529aa647b9000"},"feeGrowthOutsideX":{"v":"00"},"feeGrowthOutsideY":{"v":"00"},"secondsPerLiquidityOutside":{"v":"00"},"secondsOutside":"00","bump":254},{"pool":{"_bn":"1570e38b95fe5780c18b5e5677a7bc7091fe4b9b678d511032b7f7ac2a7bd5c3"},"index":-47600,"sign":true,"liquidityChange":{"v":"17d344798f0cc0"},"liquidityGross":{"v":"17d344798f0cc0"},"sqrtPrice":{"v":"1399c61e8b740225b000"},"feeGrowthOutsideX":{"v":"2d24a4f3781bd3dfad"},"feeGrowthOutsideY":{"v":"751df97e2f614a30"},"secondsPerLiquidityOutside":{"v":"2c"},"secondsOutside":"14080d","bump":254},{"pool":{"_bn":"1570e38b95fe5780c18b5e5677a7bc7091fe4b9b678d511032b7f7ac2a7bd5c3"},"index":-42800,"sign":false,"liquidityChange":{"v":"03111bd4fcff75"},"liquidityGross":{"v":"03111bd4fcff75"},"sqrtPrice":{"v":"18eac3a7390b98ee2000"},"feeGrowthOutsideX":{"v":"00"},"feeGrowthOutsideY":{"v":"00"},"secondsPerLiquidityOutside":{"v":"00"},"secondsOutside":"00","bump":251},{"pool":{"_bn":"1570e38b95fe5780c18b5e5677a7bc7091fe4b9b678d511032b7f7ac2a7bd5c3"},"index":-44800,"sign":true,"liquidityChange":{"v":"03111bd4fcff75"},"liquidityGross":{"v":"03111bd4fcff75"},"sqrtPrice":{"v":"168bc600cd8c58bcf000"},"feeGrowthOutsideX":{"v":"01e9f23258234723e0fe"},"feeGrowthOutsideY":{"v":"04f68728c83334dcfd"},"secondsPerLiquidityOutside":{"v":"28174a41"},"secondsOutside":"44d43c","bump":255},{"pool":{"_bn":"1570e38b95fe5780c18b5e5677a7bc7091fe4b9b678d511032b7f7ac2a7bd5c3"},"index":-43700,"sign":false,"liquidityChange":{"v":"1896c681e572aecb"},"liquidityGross":{"v":"1896c681e572aecb"},"sqrtPrice":{"v":"17d218a716af0f63f000"},"feeGrowthOutsideX":{"v":"00"},"feeGrowthOutsideY":{"v":"00"},"secondsPerLiquidityOutside":{"v":"00"},"secondsOutside":"00","bump":251}],"volumeX":"316524086500","volumeY":"3360875000"},{"timestamp":1661428800000,"ticks":[{"pool":{"_bn":"1570e38b95fe5780c18b5e5677a7bc7091fe4b9b678d511032b7f7ac2a7bd5c3"},"index":-43900,"sign":true,"liquidityChange":{"v":"1896c681e572aecb"},"liquidityGross":{"v":"1896c681e572aecb"},"sqrtPrice":{"v":"17956c185245d62ef000"},"feeGrowthOutsideX":{"v":"029efb1aa549741d5191"},"feeGrowthOutsideY":{"v":"071c124329f1314620"},"secondsPerLiquidityOutside":{"v":"2818f2f7"},"secondsOutside":"44d724","bump":255},{"pool":{"_bn":"1570e38b95fe5780c18b5e5677a7bc7091fe4b9b678d511032b7f7ac2a7bd5c3"},"index":-40200,"sign":false,"liquidityChange":{"v":"17d344798f0cc0"},"liquidityGross":{"v":"17d344798f0cc0"},"sqrtPrice":{"v":"1c60454529aa647b9000"},"feeGrowthOutsideX":{"v":"00"},"feeGrowthOutsideY":{"v":"00"},"secondsPerLiquidityOutside":{"v":"00"},"secondsOutside":"00","bump":254},{"pool":{"_bn":"1570e38b95fe5780c18b5e5677a7bc7091fe4b9b678d511032b7f7ac2a7bd5c3"},"index":-47600,"sign":true,"liquidityChange":{"v":"17d344798f0cc0"},"liquidityGross":{"v":"17d344798f0cc0"},"sqrtPrice":{"v":"1399c61e8b740225b000"},"feeGrowthOutsideX":{"v":"2d24a4f3781bd3dfad"},"feeGrowthOutsideY":{"v":"751df97e2f614a30"},"secondsPerLiquidityOutside":{"v":"2c"},"secondsOutside":"14080d","bump":254},{"pool":{"_bn":"1570e38b95fe5780c18b5e5677a7bc7091fe4b9b678d511032b7f7ac2a7bd5c3"},"index":-42800,"sign":false,"liquidityChange":{"v":"03111bd4fcff75"},"liquidityGross":{"v":"03111bd4fcff75"},"sqrtPrice":{"v":"18eac3a7390b98ee2000"},"feeGrowthOutsideX":{"v":"00"},"feeGrowthOutsideY":{"v":"00"},"secondsPerLiquidityOutside":{"v":"00"},"secondsOutside":"00","bump":251},{"pool":{"_bn":"1570e38b95fe5780c18b5e5677a7bc7091fe4b9b678d511032b7f7ac2a7bd5c3"},"index":-44800,"sign":true,"liquidityChange":{"v":"03111bd4fcff75"},"liquidityGross":{"v":"03111bd4fcff75"},"sqrtPrice":{"v":"168bc600cd8c58bcf000"},"feeGrowthOutsideX":{"v":"01e9f23258234723e0fe"},"feeGrowthOutsideY":{"v":"04f68728c83334dcfd"},"secondsPerLiquidityOutside":{"v":"28174a41"},"secondsOutside":"44d43c","bump":255},{"pool":{"_bn":"1570e38b95fe5780c18b5e5677a7bc7091fe4b9b678d511032b7f7ac2a7bd5c3"},"index":-43700,"sign":false,"liquidityChange":{"v":"1896c681e572aecb"},"liquidityGross":{"v":"1896c681e572aecb"},"sqrtPrice":{"v":"17d218a716af0f63f000"},"feeGrowthOutsideX":{"v":"00"},"feeGrowthOutsideY":{"v":"00"},"secondsPerLiquidityOutside":{"v":"00"},"secondsOutside":"00","bump":251}],"volumeX":"316524086500","volumeY":"3360875000"},{"timestamp":1661515200000,"ticks":[{"pool":{"_bn":"1570e38b95fe5780c18b5e5677a7bc7091fe4b9b678d511032b7f7ac2a7bd5c3"},"index":-42800,"sign":false,"liquidityChange":{"v":"03111bd4fcff75"},"liquidityGross":{"v":"03111bd4fcff75"},"sqrtPrice":{"v":"18eac3a7390b98ee2000"},"feeGrowthOutsideX":{"v":"00"},"feeGrowthOutsideY":{"v":"00"},"secondsPerLiquidityOutside":{"v":"00"},"secondsOutside":"00","bump":251},{"pool":{"_bn":"1570e38b95fe5780c18b5e5677a7bc7091fe4b9b678d511032b7f7ac2a7bd5c3"},"index":-44800,"sign":true,"liquidityChange":{"v":"03111bd4fcff75"},"liquidityGross":{"v":"03111bd4fcff75"},"sqrtPrice":{"v":"168bc600cd8c58bcf000"},"feeGrowthOutsideX":{"v":"01e9f23258234723e0fe"},"feeGrowthOutsideY":{"v":"04f68728c83334dcfd"},"secondsPerLiquidityOutside":{"v":"28174a41"},"secondsOutside":"44d43c","bump":255},{"pool":{"_bn":"1570e38b95fe5780c18b5e5677a7bc7091fe4b9b678d511032b7f7ac2a7bd5c3"},"index":-43900,"sign":true,"liquidityChange":{"v":"1896c681e572aecb"},"liquidityGross":{"v":"1896c681e572aecb"},"sqrtPrice":{"v":"17956c185245d62ef000"},"feeGrowthOutsideX":{"v":"029efb1aa549741d5191"},"feeGrowthOutsideY":{"v":"071c124329f1314620"},"secondsPerLiquidityOutside":{"v":"2818f2f7"},"secondsOutside":"44d724","bump":255},{"pool":{"_bn":"1570e38b95fe5780c18b5e5677a7bc7091fe4b9b678d511032b7f7ac2a7bd5c3"},"index":-40200,"sign":false,"liquidityChange":{"v":"17d344798f0cc0"},"liquidityGross":{"v":"17d344798f0cc0"},"sqrtPrice":{"v":"1c60454529aa647b9000"},"feeGrowthOutsideX":{"v":"00"},"feeGrowthOutsideY":{"v":"00"},"secondsPerLiquidityOutside":{"v":"00"},"secondsOutside":"00","bump":254},{"pool":{"_bn":"1570e38b95fe5780c18b5e5677a7bc7091fe4b9b678d511032b7f7ac2a7bd5c3"},"index":-47600,"sign":true,"liquidityChange":{"v":"17d344798f0cc0"},"liquidityGross":{"v":"17d344798f0cc0"},"sqrtPrice":{"v":"1399c61e8b740225b000"},"feeGrowthOutsideX":{"v":"2d24a4f3781bd3dfad"},"feeGrowthOutsideY":{"v":"751df97e2f614a30"},"secondsPerLiquidityOutside":{"v":"2c"},"secondsOutside":"14080d","bump":254},{"pool":{"_bn":"1570e38b95fe5780c18b5e5677a7bc7091fe4b9b678d511032b7f7ac2a7bd5c3"},"index":-43700,"sign":false,"liquidityChange":{"v":"1896c681e572aecb"},"liquidityGross":{"v":"1896c681e572aecb"},"sqrtPrice":{"v":"17d218a716af0f63f000"},"feeGrowthOutsideX":{"v":"00"},"feeGrowthOutsideY":{"v":"00"},"secondsPerLiquidityOutside":{"v":"00"},"secondsOutside":"00","bump":251}],"volumeX":"316524086500","volumeY":"3360875000"},{"timestamp":1661601600000,"ticks":[{"pool":{"_bn":"1570e38b95fe5780c18b5e5677a7bc7091fe4b9b678d511032b7f7ac2a7bd5c3"},"index":-47600,"sign":true,"liquidityChange":{"v":"17d344798f0cc0"},"liquidityGross":{"v":"17d344798f0cc0"},"sqrtPrice":{"v":"1399c61e8b740225b000"},"feeGrowthOutsideX":{"v":"2d24a4f3781bd3dfad"},"feeGrowthOutsideY":{"v":"751df97e2f614a30"},"secondsPerLiquidityOutside":{"v":"2c"},"secondsOutside":"14080d","bump":254},{"pool":{"_bn":"1570e38b95fe5780c18b5e5677a7bc7091fe4b9b678d511032b7f7ac2a7bd5c3"},"index":-44800,"sign":true,"liquidityChange":{"v":"03111bd4fcff75"},"liquidityGross":{"v":"03111bd4fcff75"},"sqrtPrice":{"v":"168bc600cd8c58bcf000"},"feeGrowthOutsideX":{"v":"01e9f23258234723e0fe"},"feeGrowthOutsideY":{"v":"04f68728c83334dcfd"},"secondsPerLiquidityOutside":{"v":"28174a41"},"secondsOutside":"44d43c","bump":255},{"pool":{"_bn":"1570e38b95fe5780c18b5e5677a7bc7091fe4b9b678d511032b7f7ac2a7bd5c3"},"index":-40200,"sign":false,"liquidityChange":{"v":"17d344798f0cc0"},"liquidityGross":{"v":"17d344798f0cc0"},"sqrtPrice":{"v":"1c60454529aa647b9000"},"feeGrowthOutsideX":{"v":"00"},"feeGrowthOutsideY":{"v":"00"},"secondsPerLiquidityOutside":{"v":"00"},"secondsOutside":"00","bump":254},{"pool":{"_bn":"1570e38b95fe5780c18b5e5677a7bc7091fe4b9b678d511032b7f7ac2a7bd5c3"},"index":-43700,"sign":false,"liquidityChange":{"v":"1896c681e572aecb"},"liquidityGross":{"v":"1896c681e572aecb"},"sqrtPrice":{"v":"17d218a716af0f63f000"},"feeGrowthOutsideX":{"v":"00"},"feeGrowthOutsideY":{"v":"00"},"secondsPerLiquidityOutside":{"v":"00"},"secondsOutside":"00","bump":251},{"pool":{"_bn":"1570e38b95fe5780c18b5e5677a7bc7091fe4b9b678d511032b7f7ac2a7bd5c3"},"index":-43900,"sign":true,"liquidityChange":{"v":"1896c681e572aecb"},"liquidityGross":{"v":"1896c681e572aecb"},"sqrtPrice":{"v":"17956c185245d62ef000"},"feeGrowthOutsideX":{"v":"029efb1aa549741d5191"},"feeGrowthOutsideY":{"v":"071c124329f1314620"},"secondsPerLiquidityOutside":{"v":"2818f2f7"},"secondsOutside":"44d724","bump":255},{"pool":{"_bn":"1570e38b95fe5780c18b5e5677a7bc7091fe4b9b678d511032b7f7ac2a7bd5c3"},"index":-42800,"sign":false,"liquidityChange":{"v":"03111bd4fcff75"},"liquidityGross":{"v":"03111bd4fcff75"},"sqrtPrice":{"v":"18eac3a7390b98ee2000"},"feeGrowthOutsideX":{"v":"00"},"feeGrowthOutsideY":{"v":"00"},"secondsPerLiquidityOutside":{"v":"00"},"secondsOutside":"00","bump":251}],"volumeX":"316524086500","volumeY":"3360875000"},{"timestamp":1661688000000,"ticks":[{"pool":{"_bn":"1570e38b95fe5780c18b5e5677a7bc7091fe4b9b678d511032b7f7ac2a7bd5c3"},"index":-47600,"sign":true,"liquidityChange":{"v":"17d344798f0cc0"},"liquidityGross":{"v":"17d344798f0cc0"},"sqrtPrice":{"v":"1399c61e8b740225b000"},"feeGrowthOutsideX":{"v":"2d24a4f3781bd3dfad"},"feeGrowthOutsideY":{"v":"751df97e2f614a30"},"secondsPerLiquidityOutside":{"v":"2c"},"secondsOutside":"14080d","bump":254},{"pool":{"_bn":"1570e38b95fe5780c18b5e5677a7bc7091fe4b9b678d511032b7f7ac2a7bd5c3"},"index":-44800,"sign":true,"liquidityChange":{"v":"03111bd4fcff75"},"liquidityGross":{"v":"03111bd4fcff75"},"sqrtPrice":{"v":"168bc600cd8c58bcf000"},"feeGrowthOutsideX":{"v":"01e9f23258234723e0fe"},"feeGrowthOutsideY":{"v":"04f68728c83334dcfd"},"secondsPerLiquidityOutside":{"v":"28174a41"},"secondsOutside":"44d43c","bump":255},{"pool":{"_bn":"1570e38b95fe5780c18b5e5677a7bc7091fe4b9b678d511032b7f7ac2a7bd5c3"},"index":-40200,"sign":false,"liquidityChange":{"v":"17d344798f0cc0"},"liquidityGross":{"v":"17d344798f0cc0"},"sqrtPrice":{"v":"1c60454529aa647b9000"},"feeGrowthOutsideX":{"v":"00"},"feeGrowthOutsideY":{"v":"00"},"secondsPerLiquidityOutside":{"v":"00"},"secondsOutside":"00","bump":254},{"pool":{"_bn":"1570e38b95fe5780c18b5e5677a7bc7091fe4b9b678d511032b7f7ac2a7bd5c3"},"index":-43700,"sign":false,"liquidityChange":{"v":"1896c681e572aecb"},"liquidityGross":{"v":"1896c681e572aecb"},"sqrtPrice":{"v":"17d218a716af0f63f000"},"feeGrowthOutsideX":{"v":"00"},"feeGrowthOutsideY":{"v":"00"},"secondsPerLiquidityOutside":{"v":"00"},"secondsOutside":"00","bump":251},{"pool":{"_bn":"1570e38b95fe5780c18b5e5677a7bc7091fe4b9b678d511032b7f7ac2a7bd5c3"},"index":-43900,"sign":true,"liquidityChange":{"v":"1896c681e572aecb"},"liquidityGross":{"v":"1896c681e572aecb"},"sqrtPrice":{"v":"17956c185245d62ef000"},"feeGrowthOutsideX":{"v":"029efb1aa549741d5191"},"feeGrowthOutsideY":{"v":"071c124329f1314620"},"secondsPerLiquidityOutside":{"v":"2818f2f7"},"secondsOutside":"44d724","bump":255},{"pool":{"_bn":"1570e38b95fe5780c18b5e5677a7bc7091fe4b9b678d511032b7f7ac2a7bd5c3"},"index":-42800,"sign":false,"liquidityChange":{"v":"03111bd4fcff75"},"liquidityGross":{"v":"03111bd4fcff75"},"sqrtPrice":{"v":"18eac3a7390b98ee2000"},"feeGrowthOutsideX":{"v":"00"},"feeGrowthOutsideY":{"v":"00"},"secondsPerLiquidityOutside":{"v":"00"},"secondsOutside":"00","bump":251}],"volumeX":"316524086500","volumeY":"3360875000"},{"timestamp":1661774400000,"ticks":[{"pool":{"_bn":"1570e38b95fe5780c18b5e5677a7bc7091fe4b9b678d511032b7f7ac2a7bd5c3"},"index":-42800,"sign":false,"liquidityChange":{"v":"03111bd4fcff75"},"liquidityGross":{"v":"03111bd4fcff75"},"sqrtPrice":{"v":"18eac3a7390b98ee2000"},"feeGrowthOutsideX":{"v":"00"},"feeGrowthOutsideY":{"v":"00"},"secondsPerLiquidityOutside":{"v":"00"},"secondsOutside":"00","bump":251},{"pool":{"_bn":"1570e38b95fe5780c18b5e5677a7bc7091fe4b9b678d511032b7f7ac2a7bd5c3"},"index":-44800,"sign":true,"liquidityChange":{"v":"03111bd4fcff75"},"liquidityGross":{"v":"03111bd4fcff75"},"sqrtPrice":{"v":"168bc600cd8c58bcf000"},"feeGrowthOutsideX":{"v":"01e9f23258234723e0fe"},"feeGrowthOutsideY":{"v":"04f68728c83334dcfd"},"secondsPerLiquidityOutside":{"v":"28174a41"},"secondsOutside":"44d43c","bump":255},{"pool":{"_bn":"1570e38b95fe5780c18b5e5677a7bc7091fe4b9b678d511032b7f7ac2a7bd5c3"},"index":-43900,"sign":true,"liquidityChange":{"v":"1896c681e572aecb"},"liquidityGross":{"v":"1896c681e572aecb"},"sqrtPrice":{"v":"17956c185245d62ef000"},"feeGrowthOutsideX":{"v":"029efb1aa549741d5191"},"feeGrowthOutsideY":{"v":"071c124329f1314620"},"secondsPerLiquidityOutside":{"v":"2818f2f7"},"secondsOutside":"44d724","bump":255},{"pool":{"_bn":"1570e38b95fe5780c18b5e5677a7bc7091fe4b9b678d511032b7f7ac2a7bd5c3"},"index":-40200,"sign":false,"liquidityChange":{"v":"17d344798f0cc0"},"liquidityGross":{"v":"17d344798f0cc0"},"sqrtPrice":{"v":"1c60454529aa647b9000"},"feeGrowthOutsideX":{"v":"00"},"feeGrowthOutsideY":{"v":"00"},"secondsPerLiquidityOutside":{"v":"00"},"secondsOutside":"00","bump":254},{"pool":{"_bn":"1570e38b95fe5780c18b5e5677a7bc7091fe4b9b678d511032b7f7ac2a7bd5c3"},"index":-47600,"sign":true,"liquidityChange":{"v":"17d344798f0cc0"},"liquidityGross":{"v":"17d344798f0cc0"},"sqrtPrice":{"v":"1399c61e8b740225b000"},"feeGrowthOutsideX":{"v":"2d24a4f3781bd3dfad"},"feeGrowthOutsideY":{"v":"751df97e2f614a30"},"secondsPerLiquidityOutside":{"v":"2c"},"secondsOutside":"14080d","bump":254},{"pool":{"_bn":"1570e38b95fe5780c18b5e5677a7bc7091fe4b9b678d511032b7f7ac2a7bd5c3"},"index":-43700,"sign":false,"liquidityChange":{"v":"1896c681e572aecb"},"liquidityGross":{"v":"1896c681e572aecb"},"sqrtPrice":{"v":"17d218a716af0f63f000"},"feeGrowthOutsideX":{"v":"00"},"feeGrowthOutsideY":{"v":"00"},"secondsPerLiquidityOutside":{"v":"00"},"secondsOutside":"00","bump":251}],"volumeX":"316524086500","volumeY":"3360875000"},{"timestamp":1661860800000,"ticks":[{"pool":{"_bn":"1570e38b95fe5780c18b5e5677a7bc7091fe4b9b678d511032b7f7ac2a7bd5c3"},"index":-42800,"sign":false,"liquidityChange":{"v":"03111bd4fcff75"},"liquidityGross":{"v":"03111bd4fcff75"},"sqrtPrice":{"v":"18eac3a7390b98ee2000"},"feeGrowthOutsideX":{"v":"00"},"feeGrowthOutsideY":{"v":"00"},"secondsPerLiquidityOutside":{"v":"00"},"secondsOutside":"00","bump":251},{"pool":{"_bn":"1570e38b95fe5780c18b5e5677a7bc7091fe4b9b678d511032b7f7ac2a7bd5c3"},"index":-44800,"sign":true,"liquidityChange":{"v":"03111bd4fcff75"},"liquidityGross":{"v":"03111bd4fcff75"},"sqrtPrice":{"v":"168bc600cd8c58bcf000"},"feeGrowthOutsideX":{"v":"01e9f23258234723e0fe"},"feeGrowthOutsideY":{"v":"04f68728c83334dcfd"},"secondsPerLiquidityOutside":{"v":"28174a41"},"secondsOutside":"44d43c","bump":255},{"pool":{"_bn":"1570e38b95fe5780c18b5e5677a7bc7091fe4b9b678d511032b7f7ac2a7bd5c3"},"index":-43900,"sign":true,"liquidityChange":{"v":"1896c681e572aecb"},"liquidityGross":{"v":"1896c681e572aecb"},"sqrtPrice":{"v":"17956c185245d62ef000"},"feeGrowthOutsideX":{"v":"029efb1aa549741d5191"},"feeGrowthOutsideY":{"v":"071c124329f1314620"},"secondsPerLiquidityOutside":{"v":"2818f2f7"},"secondsOutside":"44d724","bump":255},{"pool":{"_bn":"1570e38b95fe5780c18b5e5677a7bc7091fe4b9b678d511032b7f7ac2a7bd5c3"},"index":-40200,"sign":false,"liquidityChange":{"v":"17d344798f0cc0"},"liquidityGross":{"v":"17d344798f0cc0"},"sqrtPrice":{"v":"1c60454529aa647b9000"},"feeGrowthOutsideX":{"v":"00"},"feeGrowthOutsideY":{"v":"00"},"secondsPerLiquidityOutside":{"v":"00"},"secondsOutside":"00","bump":254},{"pool":{"_bn":"1570e38b95fe5780c18b5e5677a7bc7091fe4b9b678d511032b7f7ac2a7bd5c3"},"index":-47600,"sign":true,"liquidityChange":{"v":"17d344798f0cc0"},"liquidityGross":{"v":"17d344798f0cc0"},"sqrtPrice":{"v":"1399c61e8b740225b000"},"feeGrowthOutsideX":{"v":"2d24a4f3781bd3dfad"},"feeGrowthOutsideY":{"v":"751df97e2f614a30"},"secondsPerLiquidityOutside":{"v":"2c"},"secondsOutside":"14080d","bump":254},{"pool":{"_bn":"1570e38b95fe5780c18b5e5677a7bc7091fe4b9b678d511032b7f7ac2a7bd5c3"},"index":-43700,"sign":false,"liquidityChange":{"v":"1896c681e572aecb"},"liquidityGross":{"v":"1896c681e572aecb"},"sqrtPrice":{"v":"17d218a716af0f63f000"},"feeGrowthOutsideX":{"v":"00"},"feeGrowthOutsideY":{"v":"00"},"secondsPerLiquidityOutside":{"v":"00"},"secondsOutside":"00","bump":251}],"volumeX":"316524086500","volumeY":"3360875000"}]